Workbook

Sheet 1 MNE Group Information
B2: 1 MNE Group Information
A3: please indicate
A4: GIR401 – Ultimate Parent Entity | B4: 1.1 Identification of the Filing Constituent Entity
A5: GIR402 – Designated Filing Entity | B5: 1. UPE is the Filing Constituent Entity | C5: 2. Name of the Filing Constituent Entity | D5: 3. Tax identification number | E5: 4. Role | F5: 5. Jurisdiction where the Filing CE is located | G5: 6. Recipient Jurisdictions for Exchange of Information (if relevant)
A6: GIR403 – Designated Local Entity | B6: yes | C6: Nord Stream AG | D6: CHE-112.660.698 | E6: GIR401 – Ultimate Parent Entity | F6: Switzerland | G6: 0
A7: GIR404 – Constituent Entity | B7: FilingCE | C7: Name | D7: TIN | E7: Role
A8: GIR405 – Other
B9: 1.2 MNE Group General Information
B11: 1.2.1 MNE Group and Reporting Fiscal Year
B12: 1. Name of the MNE Group | C12: 2. Start date of the Reporting Fiscal Year | D12: 3. End date of the Reporting Fiscal Year | E12: 4. Amended Return
A13: please indicate | B13: Nord Stream | C13: 1. January 2024 | D13: 31. December 2024 | E13: no
A14: GIR501– subparagraph a | B14: NameMNE | C14: Start | D14: End
A15: GIR502 – subparagraph b
A16: GIR503 – subparagraph c | B16: 1.2.2 MNE General accounting information | E16: Consolidated Financial Statements means: Subparagraph (a) the financial statements prepared by an Entity in accordance with an Acceptable Financial Accounting Standard, in which the assets, liabilities, income, expenses and cash flows of that Entity and the Entities in which it has a Controlling Interest are presented as those of a single economic unit; Subparagraph (b) where an Entity meets the definition of a Group under Article 1.2.3, the financial statements of the Entity that are prepared in accordance with an Acceptable Financial Accounting Standard; Subparagraph (c) where the Ultimate Parent Entity has financial statements described in paragraph (a) or (b) that are not prepared in accordance with an Acceptable Financial Accounting Standard, the financial statements are those that have been prepared subject to adjustments to prevent any Material Competitive Distortions; and Subparagraph (d) where the Ultimate Parent Entity does not prepare financial statements described in the paragraphs above, the Consolidated Financial Statements of the Ultimate Parent Entity are those that would have been prepared if such Entity were required to prepare such statements in accordance with an Authorised Financial Accounting Standard that is either an Acceptable Financial Accounting Standard or another financial accounting standard that is adjusted to prevent any Material Competitive Distortions.
A17: GIR504 – subparagraph d | B17: 1. Consolidated Financial Statements of the UPE (type) | C17: 2. Financial Accounting standard used for the CFS of the UPE | D17: 3. Presentation currency used for the CFS of the UPE (ISO code)
B18: GIR501– subparagraph a | C18: IFRS | D18: USD
C19: FAS | D19: Currency
B21: 1.3 Corporate Structure
A23: please indicate | B23: 1.3.1 Ultimate Parent Entity
A24: GIR201 – QIIR applicable to Low-Taxed Constituent Entities located in other jurisdictions only | B24: 1. UPE Jurisdiction | C24: Switzerland
A25: GIR202 – QIIR applicable to both Low-Taxed Constituent Entities located in other jurisdictions and in the jurisdiction of the Parent Entity | B25: 2. Applicable rules? | C25: GIR202 – QIIR applicable to both Low-Taxed Constituent Entities located in other jurisdictions and in the jurisdiction of the Parent Entity | D25: Rules
A26: GIR203 – QUTPR | B26: 3. Name of the UPE | C26: Nord Stream AG | D26: UPE
A27: GIR204 – QDMTT | B27: 4. TIN of the UPE | C27: CHE-112.660.698 | D27: TIN
A28: GIR205 – Not applicable | B28: 5. TIN of the UPE in the Filing Jurisdiction (if different, and if any) | C28: not applicable
B29: 6. Status for GloBE purposes | C29: GIR301 – Constituent Entity | D29: GlobeStatus
B30: 7. If the UPE is an Excluded Entity - Type | C30: not applicable | D30: ExcludedUPEStatus
B31: 8. Art. 10.3.5 Jurisdiction (if any) | C31: not applicable | D31: Art10.3.5
B33: 1.3.2 Group Entities (other than the UPE) and members of JV Groups
B34: 1.3.2.1 Constituent Entities and members of JV Groups
B35: Changes | C35: 1. Changes from previous Reporting Fiscal Year? | D35: no
B36: Jurisdiction
B37: 2. Jurisdiction | C37: Switzerland | D37: Germany | E37: Russia | F37: X5 | G37: X5 | H37: X5 | I37: X5
B38: 3. Applicable rules? | C38: GIR202 – QIIR applicable to both Low-Taxed Constituent Entities located in other jurisdictions and in the jurisdiction of the Parent Entity | D38: GIR202 – QIIR applicable to both Low-Taxed Constituent Entities located in other jurisdictions and in the jurisdiction of the Parent Entity | E38: GIR205 – Not applicable | F38: GIR205 – Not applicable | G38: GIR205 – Not applicable | H38: GIR205 – Not applicable | I38: GIR205 – Not applicable
B39: Identification of the Constituent Entity, JV or JV Subsidiary
B40: 4. Name of Constituent Entity, JV or JV Subsidiary | C40: Nord Stream AG | D40: Nord Stream AG (PE Germany) | E40: Nord Stream AG (PE Russia) | F40: Nord Stream AG (Stateless Permanent Establishment Germany) | G40: Nord Stream AG (Stateless Permanent Establishment Denmark) | H40: Nord Stream AG (Stateless Permanent Establishment Sweden) | I40: Nord Stream AG (Stateless Permanent Establishment Finland)
B41: 5. TIN | C41: CHE-112.660.698 | F41: Stateless | G41: Stateless | H41: Stateless | I41: Stateless
B42: 6. TIN for filing jurisdiction (if any)
B43: 7. Status for GloBE purposes | C43: GIR301 – Constituent Entity | D43: GIR305 – Permanent Establishment | E43: GIR305 – Permanent Establishment | F43: GIR305 – Permanent Establishment | G43: GIR305 – Permanent Establishment | H43: GIR305 – Permanent Establishment | I43: GIR305 – Permanent Establishment
B44: Ownership structure of the Constituent Entity, JV or JV Subsidiary. For each entity holding Ownership interests in the Constituent Entity, JV or JV Subsidiary:
B45: 8. Type | C45: GIR801 – UPE | D45: GIR802 – Constituent Entities | E45: GIR802 – Constituent Entities | F45: GIR802 – Constituent Entities | G45: GIR802 – Constituent Entities | H45: GIR802 – Constituent Entities | I45: GIR802 – Constituent Entities
B46: 9. TIN (for CEs or members of JV Groups)
B47: 10. Ownership interest held (percentage) | C47: 1 | D47: 1 | E47: 1 | F47: 1 | G47: 1 | H47: 1 | I47: 1
B48: If the CE is a POPE or an Intermediate Parent Entity, is the Entity required to apply a QIIR?
B49: 11. Parent Entity Status | C49: not applicable | D49: not applicable | E49: not applicable | F49: not applicable | G49: not applicable | H49: not applicable | I49: not applicable
B50: 12. If the exception provided in Article 2.1.3 shall apply, such that the UPE applies the IIR or there is another Intermediate Parent Entity required to apply the IIR, identify the UPE or the other Intermediate Parent Entity (TIN) | C50: not applicable | D50: not applicable | E50: not applicable | F50: not applicable | G50: not applicable | H50: not applicable | I50: not applicable
B51: 13. If the exception provided in Article 2.1.5 shall apply, identify the other POPE required to apply a QIIR (TIN) | C51: not applicable | D51: not applicable | E51: not applicable | F51: not applicable | G51: not applicable | H51: not applicable | I51: not applicable
B52: Is UTPR applicable in respect of the entity? | C52: please indicate yes or no
A53: please indicate yes or no | B53: 14. Initial phase of International Activity (Article 9.3.1 or Article 9.3.5 (a)) applicable? | C53: no | D53: no | E53: no | F53: no | G53: no | H53: no | I53: no
A54: yes | B54: 15. Aggregate Ownership Interests (respectively Allocable Share of Top-up Taxes) of Parent Entities required to apply a QIIR in respect of the CE (respectively member of JV Group) (in percentage) | C54: 0 | D54: 0 | E54: 0 | F54: 0 | G54: 0 | H54: 0 | I54: 0 | Y54: The AggOwnership element indicates the aggregate Ownership Interests in percentage over the total of Ownership Interests held in that Constituent Entity. The aggregate (direct and indirect) Ownership Interests of Parent Entities required to apply a QIIR is the sum of the Ownership Interests held by each Parent Entity that is required to apply a QIIR with respect to the Low-Taxed Constituent Entities. The aggregate amount shall be zero if no Parent Entity is required to apply a QIIR in respect of the low- taxed income of the LowTaxed Constituent Entity. If a Parent Entity (that owns an Ownership Interest in a LTCE indirectly through an Intermediate Parent Entity or a Partially-Owned Parent Entity that is not eligible for an exclusion from the IIR under Article 2.1.3 or 2.1.5) is required to apply the IIR, the relevant Ownership Interests shall be counted only once for purposes of computing the aggregate amount
A55: no | B55: 16. Are the UPE's Ownership Interests in the CE (respectively UPE’s allocable share of Top-up Tax for the member of JV Group) greater the aggregate Ownership Interests (respectively allocable share) of Parent Entities required to apply a QIIR in that CE (respectively member of JV group)? | C55: please indicate yes or no | D55: please indicate yes or no | E55: please indicate yes or no | F55: please indicate yes or no | G55: please indicate yes or no | H55: please indicate yes or no | I55: please indicate yes or no
B57: 1.3.2.2 Excluded Entities
B58: 1. Changes from previous Reporting Fiscal Year? | C58: no
B59: 2. Name of the Excluded Entity | C59: not applicable
B60: 3. Type of the Excluded Entity | C60: not applicable
B62: 1.3.3 Changes in the corporate structure that occurred during the Reporting Fiscal Year
B63: a. Were changes in the corporate structure that occurred during the Reporting Fiscal Year not reported because they neither affected the ETR computation orthe computation or allocation of Top-up Tax? | C63: no
B65: 1.4 High-level summary of GloBE Information
B66: 1. Name of the Constituent Entity (or other Entity of the MNEGroup) or member of JV Group | C66: =+C40 -> Nord Stream AG | D66: =+D40 -> Nord Stream AG (PE Germany) | E66: =+E40 -> Nord Stream AG (PE Russia) | F66: =+F40 -> Nord Stream AG (Stateless Permanent Establishment Germany) | G66: =+G40 -> Nord Stream AG (Stateless Permanent Establishment Denmark) | H66: =+H40 -> Nord Stream AG (Stateless Permanent Establishment Sweden) | I66: =+I40 -> Nord Stream AG (Stateless Permanent Establishment Finland) | J66: =+J40 -> 0 | ... X66: =+X40 -> 0
B67: 2. TIN | C67: =+C41 -> CHE-112.660.698 | D67: =+D41 -> 0 | E67: =+E41 -> 0 | F67: =+F41 -> Stateless | G67: =+G41 -> Stateless | H67: =+H41 -> Stateless | I67: =+I41 -> Stateless | J67: =+J41 -> 0 | ... X67: =+X41 -> 0
B68: 3.Effective Date of the change | C68: not applicable | D68: not applicable | E68: not applicable | F68: not applicable | G68: not applicable | H68: not applicable | I68: not applicable | J68: not applicable | K68: not applicable | L68: not applicable | M68: not applicable | N68: not applicable | O68: not applicable | P68: not applicable | Q68: not applicable | R68: not applicable | S68: not applicable | T68: not applicable | U68: not applicable | V68: not applicable | W68: not applicable | X68: not applicable
B69: 4. Status for GloBE purposes before the change | C69: not applicable | D69: not applicable | E69: not applicable | F69: not applicable | G69: not applicable | H69: not applicable | I69: not applicable | J69: not applicable | K69: not applicable | L69: not applicable | M69: not applicable | N69: not applicable | O69: not applicable | P69: not applicable | Q69: not applicable | R69: not applicable | S69: not applicable | T69: not applicable | U69: not applicable | V69: not applicable | W69: not applicable | X69: not applicable
B70: 5. Status for GloBE purposes after the change | C70: not applicable | D70: not applicable | E70: not applicable | F70: not applicable | G70: not applicable | H70: not applicable | I70: not applicable | J70: not applicable | K70: not applicable | L70: not applicable | M70: not applicable | N70: not applicable | O70: not applicable | P70: not applicable | Q70: not applicable | R70: not applicable | S70: not applicable | T70: not applicable | U70: not applicable | V70: not applicable | W70: not applicable | X70: not applicable
B71: 6. Entities holding Ownership interests in that CE (or other Entity) or member of JV Group before or after the change | C71: not applicable | D71: not applicable | E71: not applicable | F71: not applicable | G71: not applicable | H71: not applicable | I71: not applicable | J71: not applicable | K71: not applicable | L71: not applicable | M71: not applicable | N71: not applicable | O71: not applicable | P71: not applicable | Q71: not applicable | R71: not applicable | S71: not applicable | T71: not applicable | U71: not applicable | V71: not applicable | W71: not applicable | X71: not applicable
B72: 7. Ownership Interests held in that CE (or other Entity) or member of JV Group before the change (Percentage) | C72: not applicable | D72: not applicable | E72: not applicable | F72: not applicable | G72: not applicable | H72: not applicable | I72: not applicable | J72: not applicable | K72: not applicable | L72: not applicable | M72: not applicable | N72: not applicable | O72: not applicable | P72: not applicable | Q72: not applicable | R72: not applicable | S72: not applicable | T72: not applicable | U72: not applicable | V72: not applicable | W72: not applicable | X72: not applicable
B73: 8. Ownership Interests held in that CE (or other Entity) or member of JV Group after the change (Percentage) | C73: not applicable | D73: not applicable | E73: not applicable | F73: not applicable | G73: not applicable | H73: not applicable | I73: not applicable | J73: not applicable | K73: not applicable | L73: not applicable | M73: not applicable | N73: not applicable | O73: not applicable | P73: not applicable | Q73: not applicable | R73: not applicable | S73: not applicable | T73: not applicable | U73: not applicable | V73: not applicable | W73: not applicable | X73: not applicable
C76: not applicable
B77: GIR301 – Constituent Entity | C77: GIR601 – Governmental Entity | D77: GIR801 – UPE
B78: GIR302 – Flow-through Entity – Tax Transparent | C78: GIR602 – International Organisation | D78: GIR802 – Constituent Entities
B79: GIR303 – Flow-through Entity – Reverse Hybrid | C79: GIR603 – Non-profit Organisation | D79: GIR803 – JV’s
B80: GIR304 – Hybrid Entity | C80: GIR604 – Pension fund | D80: GIR804 – JV Subsidiaries
B81: GIR305 – Permanent Establishment | C81: GIR605 – Investment Fund that is the UPE | D81: GIR805 – Excluded Entities (aggregate)
B82: GIR306 – Main Entity | C82: GIR606 – Real Estate Investment Vehicle that is the UPE | D82: GIR806 – Non-Group members (aggregate).
B83: GIR307 – Minority-Owned Parent Entity
B84: GIR308 – Minority-Owned Subsidiary
B85: GIR309 – Minority-Owned Constituent Entity
B86: GIR310 – Investment Entity
B87: GIR311 – Insurance Investment Entity
B88: GIR312 – Securitisation Entity
B89: GIR313 – JV
B90: GIR314 – JV Subsidiary
B91: GIR315 – Non-Material Constituent Entity
B92: GIR316 – Excluded Entity
B93: GIR317 – Parent Entity required to apply a QIIR under Article 10.3.5
B94: GIR318 – Non-group member

Sheet 2 Safe Harbours CH
B2: 2. Jurisdictional safe harbours and exclusions – Jurisdictional schedules
B3: The Filing Constituent Entity shall complete Section 2 on a jurisdictional basis, for each jurisdiction where exceptions to the GloBE computation apply.
B5: 2.1. Characteristics of the jurisdiction
B6: 1. Name of the jurisdiction | C6: Switzerland
B7: 2. Type of subgroup (if any) | C7: not applicable
B8: 3. Identification of subgroup (if any) | C8: not applicable
B9: 4. Jurisdiction with taxing rights | C9: =+C6 -> Switzerland
A10: please indicate yes or no | B10: 5. Existence of reportable differences (Yes/No) | C10: no
A11: yes
A12: no | B12: 2.2. Jurisdictional exceptions applicable in respect of this jurisdiction (Top-up Tax reduced to zero)
B14: 2.2.1. Safe harbour jurisdiction election
B15: 2.2.1.1 Safe harbour election
A16: please indicate | B16: Name of the jurisdiction | C16: =+C6 -> Switzerland
A17: Permanent safe harbours | B17: 1. Safe Harbour elected | C17: GIR1202 – QDMTT safe harbour
A18: Transitional safe harbours
A19: not applicable | B19: 2.2.1.2 Permanent safe harbours
B20: (a) Simplified Calculation for Non-material Constituent Entities
B21: 1. Total Revenue of all NMCEs in the jurisdiction
B22: =+B16 -> Name of the jurisdiction | C22: =+C16 -> Switzerland
B23: a. Reporting Fiscal Year
B24: b. 1st preceding Fiscal Year (if applicable)
B25: c. 2nd preceding Fiscal Year (if applicable)
B26: d. Average of the three Fiscal Years (ifapplicable)
B27: 2. Aggregate Simplified Tax of all NMCEs in the jurisdiction
B28: =+B22 -> Name of the jurisdiction | C28: =+C22 -> Switzerland
B29: a. Reporting Fiscal Year
B30: b. 1st preceding Fiscal Year (if applicable)
B31: c. 2nd preceding Fiscal Year (if applicable)
B32: d. Average of the three Fiscal Years (ifapplicable)
B34: 2.2.1.3 Transitional safe harbours
B35: (a) Transitional CbCR safe harbour
B36: =+B22 -> Name of the jurisdiction | C36: =+C28 -> Switzerland
B37: 1. Total Revenue | C37: 34
B38: 2. Profit (Loss) before Income Tax | C38: 234
B39: 3. Simplified Covered Taxes | C39: 4332
B41: (b) Transitional UTPR safe harbour
B42: 1. Corporate income tax rate
B44: 2.2.2. Election for de minimis exclusion
B45: Election to apply the de minimis exclusion for the Reporting Fiscal Year | C45: no
B46: Simplified Calculations for Non-material Constituent Entities – Constituent Entities that are not NMCEs | C46: no
B47: 1. Revenue (Financial Accounts)
B48: a. Reporting Fiscal Year
B49: b. 1st preceding FiscalYear (if applicable)
B50: c. 2nd preceding FiscalYear (if applicable)
B51: d. Average of the three Fiscal Years
B52: 2. GloBE Revenue
B53: a. Reporting Fiscal Year
B54: b. 1st preceding FiscalYear (if applicable)
B55: c. 2nd preceding FiscalYear (if applicable)
B56: d. Average of the three Fiscal Years
B57: 3. Financial Accounting Net Income (or Loss)
B58: a. Reporting Fiscal Year
... B88: GIR1209 – Permanent Safe Harbour – Routine profit test

Sheet 2 Safe Harbours DE
B2: 2. Jurisdictional safe harbours and exclusions – Jurisdictional schedules
B3: The Filing Constituent Entity shall complete Section 2 on a jurisdictional basis, for each jurisdiction where exceptions to the GloBE computation apply.
B5: 2.1. Characteristics of the jurisdiction
B6: 1. Name of the jurisdiction | C6: Germany
B7: 2. Type of subgroup (if any) | C7: not applicable
B8: 3. Identification of subgroup (if any) | C8: not applicable
B9: 4. Jurisdiction with taxing rights | C9: =+C6 -> Germany
A10: please indicate yes or no | B10: 5. Existence of reportable differences (Yes/No) | C10: no
A11: yes
A12: no | B12: 2.2. Jurisdictional exceptions applicable in respect of this jurisdiction (Top-up Tax reduced to zero)
B14: 2.2.1. Safe harbour jurisdiction election
B15: 2.2.1.1 Safe harbour election
A16: please indicate | B16: Name of the jurisdiction | C16: =+C6 -> Germany
A17: Permanent safe harbours | B17: 1. Safe Harbour elected | C17: GIR1202 – QDMTT safe harbour
A18: Transitional safe harbours
A19: not applicable | B19: 2.2.1.2 Permanent safe harbours
B20: (a) Simplified Calculation for Non-material Constituent Entities
B21: 1. Total Revenue of all NMCEs in the jurisdiction
B22: =+B16 -> Name of the jurisdiction | C22: =+C16 -> Germany
B23: a. Reporting Fiscal Year
B24: b. 1st preceding Fiscal Year (if applicable)
B25: c. 2nd preceding Fiscal Year (if applicable)
B26: d. Average of the three Fiscal Years (ifapplicable)
B27: 2. Aggregate Simplified Tax of all NMCEs in the jurisdiction
B28: =+B22 -> Name of the jurisdiction | C28: =+C22 -> Germany
B29: a. Reporting Fiscal Year
B30: b. 1st preceding Fiscal Year (if applicable)
B31: c. 2nd preceding Fiscal Year (if applicable)
B32: d. Average of the three Fiscal Years (ifapplicable)
B34: 2.2.1.3 Transitional safe harbours
B35: (a) Transitional CbCR safe harbour
B36: =+B22 -> Name of the jurisdiction | C36: =+C28 -> Germany
B37: 1. Total Revenue | C37: 234554
B38: 2. Profit (Loss) before Income Tax | C38: 86875
B39: 3. Simplified Covered Taxes | C39: 4543
B41: (b) Transitional UTPR safe harbour
B42: 1. Corporate income tax rate
B44: 2.2.2. Election for de minimis exclusion
B45: Election to apply the de minimis exclusion for the Reporting Fiscal Year | C45: no
B46: Simplified Calculations for Non-material Constituent Entities – Constituent Entities that are not NMCEs | C46: no
B47: 1. Revenue (Financial Accounts)
B48: a. Reporting Fiscal Year
B49: b. 1st preceding FiscalYear (if applicable)
B50: c. 2nd preceding FiscalYear (if applicable)
B51: d. Average of the three Fiscal Years
B52: 2. GloBE Revenue
B53: a. Reporting Fiscal Year
B54: b. 1st preceding FiscalYear (if applicable)
B55: c. 2nd preceding FiscalYear (if applicable)
B56: d. Average of the three Fiscal Years
B57: 3. Financial Accounting Net Income (or Loss)
B58: a. Reporting Fiscal Year
... B88: GIR1209 – Permanent Safe Harbour – Routine profit test

Sheet 2 Safe Harbours RU
B2: 2. Jurisdictional safe harbours and exclusions – Jurisdictional schedules
B3: The Filing Constituent Entity shall complete Section 2 on a jurisdictional basis, for each jurisdiction where exceptions to the GloBE computation apply.
B5: 2.1. Characteristics of the jurisdiction
B6: 1. Name of the jurisdiction | C6: Russia
B7: 2. Type of subgroup (if any) | C7: not applicable
B8: 3. Identification of subgroup (if any) | C8: not applicable
B9: 4. Jurisdiction with taxing rights | C9: =+C6 -> Russia
A10: please indicate yes or no | B10: 5. Existence of reportable differences (Yes/No) | C10: no
A11: yes
A12: no | B12: 2.2. Jurisdictional exceptions applicable in respect of this jurisdiction (Top-up Tax reduced to zero)
B14: 2.2.1. Safe harbour jurisdiction election
B15: 2.2.1.1 Safe harbour election
A16: please indicate | B16: Name of the jurisdiction | C16: =+C6 -> Russia
A17: Permanent safe harbours | B17: 1. Safe Harbour elected | C17: not applicable
A18: Transitional safe harbours
A19: not applicable | B19: 2.2.1.2 Permanent safe harbours
B20: (a) Simplified Calculation for Non-material Constituent Entities
B21: 1. Total Revenue of all NMCEs in the jurisdiction
B22: =+B16 -> Name of the jurisdiction | C22: =+C16 -> Russia
B23: a. Reporting Fiscal Year
B24: b. 1st preceding Fiscal Year (if applicable)
B25: c. 2nd preceding Fiscal Year (if applicable)
B26: d. Average of the three Fiscal Years (ifapplicable)
B27: 2. Aggregate Simplified Tax of all NMCEs in the jurisdiction
B28: =+B22 -> Name of the jurisdiction | C28: =+C22 -> Russia
B29: a. Reporting Fiscal Year
B30: b. 1st preceding Fiscal Year (if applicable)
B31: c. 2nd preceding Fiscal Year (if applicable)
B32: d. Average of the three Fiscal Years (ifapplicable)
B34: 2.2.1.3 Transitional safe harbours
B35: (a) Transitional CbCR safe harbour
B36: =+B22 -> Name of the jurisdiction | C36: =+C28 -> Russia
B37: 1. Total Revenue | C37: 345443
B38: 2. Profit (Loss) before Income Tax | C38: 33433
B39: 3. Simplified Covered Taxes | C39: 344455
B41: (b) Transitional UTPR safe harbour
B42: 1. Corporate income tax rate
B44: 2.2.2. Election for de minimis exclusion
B45: Election to apply the de minimis exclusion for the Reporting Fiscal Year | C45: no
B46: Simplified Calculations for Non-material Constituent Entities – Constituent Entities that are not NMCEs | C46: no
B47: 1. Revenue (Financial Accounts)
B48: a. Reporting Fiscal Year
B49: b. 1st preceding FiscalYear (if applicable)
B50: c. 2nd preceding FiscalYear (if applicable)
B51: d. Average of the three Fiscal Years
B52: 2. GloBE Revenue
B53: a. Reporting Fiscal Year
B54: b. 1st preceding FiscalYear (if applicable)
B55: c. 2nd preceding FiscalYear (if applicable)
B56: d. Average of the three Fiscal Years
B57: 3. Financial Accounting Net Income (or Loss)
B58: a. Reporting Fiscal Year
... B88: GIR1209 – Permanent Safe Harbour – Routine profit test

Sheet 2 Safe Harbours DK
B2: 2. Jurisdictional safe harbours and exclusions – Jurisdictional schedules
B3: The Filing Constituent Entity shall complete Section 2 on a jurisdictional basis, for each jurisdiction where exceptions to the GloBE computation apply.
B5: 2.1. Characteristics of the jurisdiction
B6: 1. Name of the jurisdiction | C6: Denmark
B7: 2. Type of subgroup (if any) | C7: not applicable
B8: 3. Identification of subgroup (if any) | C8: not applicable
B9: 4. Jurisdiction with taxing rights | C9: =+C6 -> Denmark
A10: please indicate yes or no | B10: 5. Existence of reportable differences (Yes/No) | C10: no
A11: yes
A12: no | B12: 2.2. Jurisdictional exceptions applicable in respect of this jurisdiction (Top-up Tax reduced to zero)
B14: 2.2.1. Safe harbour jurisdiction election
B15: 2.2.1.1 Safe harbour election
A16: please indicate | B16: Name of the jurisdiction | C16: =+C6 -> Denmark
A17: Permanent safe harbours | B17: 1. Safe Harbour elected | C17: GIR1202 – QDMTT safe harbour
A18: Transitional safe harbours
A19: not applicable | B19: 2.2.1.2 Permanent safe harbours
B20: (a) Simplified Calculation for Non-material Constituent Entities
B21: 1. Total Revenue of all NMCEs in the jurisdiction
B22: =+B16 -> Name of the jurisdiction | C22: =+C16 -> Denmark
B23: a. Reporting Fiscal Year
B24: b. 1st preceding Fiscal Year (if applicable)
B25: c. 2nd preceding Fiscal Year (if applicable)
B26: d. Average of the three Fiscal Years (ifapplicable)
B27: 2. Aggregate Simplified Tax of all NMCEs in the jurisdiction
B28: =+B22 -> Name of the jurisdiction | C28: =+C22 -> Denmark
B29: a. Reporting Fiscal Year
B30: b. 1st preceding Fiscal Year (if applicable)
B31: c. 2nd preceding Fiscal Year (if applicable)
B32: d. Average of the three Fiscal Years (ifapplicable)
B34: 2.2.1.3 Transitional safe harbours
B35: (a) Transitional CbCR safe harbour
B36: =+B22 -> Name of the jurisdiction | C36: =+C28 -> Denmark
B37: 1. Total Revenue | C37: 876456
B38: 2. Profit (Loss) before Income Tax | C38: 4576
B39: 3. Simplified Covered Taxes | C39: 123876
B41: (b) Transitional UTPR safe harbour
B42: 1. Corporate income tax rate
B44: 2.2.2. Election for de minimis exclusion
B45: Election to apply the de minimis exclusion for the Reporting Fiscal Year | C45: no
B46: Simplified Calculations for Non-material Constituent Entities – Constituent Entities that are not NMCEs | C46: no
B47: 1. Revenue (Financial Accounts)
B48: a. Reporting Fiscal Year
B49: b. 1st preceding FiscalYear (if applicable)
B50: c. 2nd preceding FiscalYear (if applicable)
B51: d. Average of the three Fiscal Years
B52: 2. GloBE Revenue
B53: a. Reporting Fiscal Year
B54: b. 1st preceding FiscalYear (if applicable)
B55: c. 2nd preceding FiscalYear (if applicable)
B56: d. Average of the three Fiscal Years
B57: 3. Financial Accounting Net Income (or Loss)
B58: a. Reporting Fiscal Year
... B88: GIR1209 – Permanent Safe Harbour – Routine profit test

Sheet 2 Safe Harbours SE
B2: 2. Jurisdictional safe harbours and exclusions – Jurisdictional schedules
B3: The Filing Constituent Entity shall complete Section 2 on a jurisdictional basis, for each jurisdiction where exceptions to the GloBE computation apply.
B5: 2.1. Characteristics of the jurisdiction
B6: 1. Name of the jurisdiction | C6: Sweden
B7: 2. Type of subgroup (if any) | C7: not applicable
B8: 3. Identification of subgroup (if any) | C8: not applicable
B9: 4. Jurisdiction with taxing rights | C9: =+C6 -> Sweden
A10: please indicate yes or no | B10: 5. Existence of reportable differences (Yes/No) | C10: no
A11: yes
A12: no | B12: 2.2. Jurisdictional exceptions applicable in respect of this jurisdiction (Top-up Tax reduced to zero)
B14: 2.2.1. Safe harbour jurisdiction election
B15: 2.2.1.1 Safe harbour election
A16: please indicate | B16: Name of the jurisdiction | C16: =+C6 -> Sweden
A17: Permanent safe harbours | B17: 1. Safe Harbour elected | C17: GIR1202 – QDMTT safe harbour
A18: Transitional safe harbours
A19: not applicable | B19: 2.2.1.2 Permanent safe harbours
B20: (a) Simplified Calculation for Non-material Constituent Entities
B21: 1. Total Revenue of all NMCEs in the jurisdiction
B22: =+B16 -> Name of the jurisdiction | C22: =+C16 -> Sweden
B23: a. Reporting Fiscal Year
B24: b. 1st preceding Fiscal Year (if applicable)
B25: c. 2nd preceding Fiscal Year (if applicable)
B26: d. Average of the three Fiscal Years (ifapplicable)
B27: 2. Aggregate Simplified Tax of all NMCEs in the jurisdiction
B28: =+B22 -> Name of the jurisdiction | C28: =+C22 -> Sweden
B29: a. Reporting Fiscal Year
B30: b. 1st preceding Fiscal Year (if applicable)
B31: c. 2nd preceding Fiscal Year (if applicable)
B32: d. Average of the three Fiscal Years (ifapplicable)
B34: 2.2.1.3 Transitional safe harbours
B35: (a) Transitional CbCR safe harbour
B36: =+B22 -> Name of the jurisdiction | C36: =+C28 -> Sweden
B37: 1. Total Revenue | C37: 435876
B38: 2. Profit (Loss) before Income Tax | C38: 45789876
B39: 3. Simplified Covered Taxes | C39: 345687
B41: (b) Transitional UTPR safe harbour
B42: 1. Corporate income tax rate
B44: 2.2.2. Election for de minimis exclusion
B45: Election to apply the de minimis exclusion for the Reporting Fiscal Year | C45: no
B46: Simplified Calculations for Non-material Constituent Entities – Constituent Entities that are not NMCEs | C46: no
B47: 1. Revenue (Financial Accounts)
B48: a. Reporting Fiscal Year
B49: b. 1st preceding FiscalYear (if applicable)
B50: c. 2nd preceding FiscalYear (if applicable)
B51: d. Average of the three Fiscal Years
B52: 2. GloBE Revenue
B53: a. Reporting Fiscal Year
B54: b. 1st preceding FiscalYear (if applicable)
B55: c. 2nd preceding FiscalYear (if applicable)
B56: d. Average of the three Fiscal Years
B57: 3. Financial Accounting Net Income (or Loss)
B58: a. Reporting Fiscal Year
... B88: GIR1209 – Permanent Safe Harbour – Routine profit test

Sheet 2 Safe Harbours FI
B2: 2. Jurisdictional safe harbours and exclusions – Jurisdictional schedules
B3: The Filing Constituent Entity shall complete Section 2 on a jurisdictional basis, for each jurisdiction where exceptions to the GloBE computation apply.
B5: 2.1. Characteristics of the jurisdiction
B6: 1. Name of the jurisdiction | C6: Finland
B7: 2. Type of subgroup (if any) | C7: not applicable
B8: 3. Identification of subgroup (if any) | C8: not applicable
B9: 4. Jurisdiction with taxing rights | C9: =+C6 -> Finland
A10: please indicate yes or no | B10: 5. Existence of reportable differences (Yes/No) | C10: no
A11: yes
A12: no | B12: 2.2. Jurisdictional exceptions applicable in respect of this jurisdiction (Top-up Tax reduced to zero)
B14: 2.2.1. Safe harbour jurisdiction election
B15: 2.2.1.1 Safe harbour election
A16: please indicate | B16: Name of the jurisdiction | C16: =+C6 -> Finland
A17: Permanent safe harbours | B17: 1. Safe Harbour elected | C17: GIR1202 – QDMTT safe harbour
A18: Transitional safe harbours
A19: not applicable | B19: 2.2.1.2 Permanent safe harbours
B20: (a) Simplified Calculation for Non-material Constituent Entities
B21: 1. Total Revenue of all NMCEs in the jurisdiction
B22: =+B16 -> Name of the jurisdiction | C22: =+C16 -> Finland
B23: a. Reporting Fiscal Year
B24: b. 1st preceding Fiscal Year (if applicable)
B25: c. 2nd preceding Fiscal Year (if applicable)
B26: d. Average of the three Fiscal Years (ifapplicable)
B27: 2. Aggregate Simplified Tax of all NMCEs in the jurisdiction
B28: =+B22 -> Name of the jurisdiction | C28: =+C22 -> Finland
B29: a. Reporting Fiscal Year
B30: b. 1st preceding Fiscal Year (if applicable)
B31: c. 2nd preceding Fiscal Year (if applicable)
B32: d. Average of the three Fiscal Years (ifapplicable)
B34: 2.2.1.3 Transitional safe harbours
B35: (a) Transitional CbCR safe harbour
B36: =+B22 -> Name of the jurisdiction | C36: =+C28 -> Finland
B37: 1. Total Revenue | C37: 3456876
B38: 2. Profit (Loss) before Income Tax | C38: 45678765
B39: 3. Simplified Covered Taxes | C39: 465
B41: (b) Transitional UTPR safe harbour
B42: 1. Corporate income tax rate
B44: 2.2.2. Election for de minimis exclusion
B45: Election to apply the de minimis exclusion for the Reporting Fiscal Year | C45: no
B46: Simplified Calculations for Non-material Constituent Entities – Constituent Entities that are not NMCEs | C46: no
B47: 1. Revenue (Financial Accounts)
B48: a. Reporting Fiscal Year
B49: b. 1st preceding FiscalYear (if applicable)
B50: c. 2nd preceding FiscalYear (if applicable)
B51: d. Average of the three Fiscal Years
B52: 2. GloBE Revenue
B53: a. Reporting Fiscal Year
B54: b. 1st preceding FiscalYear (if applicable)
B55: c. 2nd preceding FiscalYear (if applicable)
B56: d. Average of the three Fiscal Years
B57: 3. Financial Accounting Net Income (or Loss)
B58: a. Reporting Fiscal Year
... B88: GIR1209 – Permanent Safe Harbour – Routine profit test

Sheet 3 GloBE Computations CH
D2: 3 GloBE Computations
D3: The Filing Constituent Entity shall complete Section 3 on a jurisdictional basis, for each jurisdiction (or subgroup, where relevant) where exceptions to the GloBE computation do not apply
D5: Please make sure that only the yellow marked cells are populated. Don't include or delete any other cell, row or column! | E5: To be populated
D6: References to GloBE Information Return (Pillar Two) XML Schema User Guide for Tax Administrations are in light clue | E6: XML references
D7: Further explanations are in light green | E7: Further explanations
D9: 3.1 Characteristics of the jurisdiction (Information purpose only)
D10: 1. Name of the jurisdiction | E10: Switzerland
D11: 2. Type of subgroup (if any) - mention "n/a" if no subgroup exists | E11: n/a
D12: 3. Identification of subgroup (if any) for the ETR and Top-up Tax computation - mention "n/a" if no subgroup exists | E12: n/a
D13: 4. Jurisdictions with taxing rights | E13: Switzerland
D14: 5. ETR | E14: =+E36 -> 0.015049035
D15: 6. Adjusted Covered Taxes | E15: =+E35 -> 3582188
D16: 7. Net GloBE Income or Loss | E16: =+E33 -> 238034398
D17: 8. Substance-based Income Exclusion | E17: =+E437 -> 341400
D18: 9. Additional Current Top-up Tax | E18: =+E475 -> 0
D19: 10.Top-up Tax amount under domestic legislation | E19: =+E425 -> 32076899
D20: 11. Elections
D21: 12. Aggregate current tax expense with respect to Covered Taxes after allocations in Article 4.3 | E21: =+E73 -> 3457864
D22: 13. Qualified Refundable Tax Credits or Marketable Transferable Tax Credits (tax expense) | E22: =+E78 -> 0
D23: 14. Other tax credits (tax expense) | E23: =+E81 -> 0
D24: 15. Deferred tax expense amount | E24: =+F123 -> 124324
D25: 16. Qualified Refundable Tax Credits or Marketable Transferable Tax Credits (income) | E25: =+E55 -> 0
D26: 17. Excess Negative Tax Expense Carry Forward | E26: =E93 -> 0
D27: 18. Transition Rules
D30: 3.2 ETR computation | E30: applicable
D31: 3.2.1 ETR | E31: applicable | F31: OverallComputation
D32: a. Financial Accounting Net Income or Loss | E32: =+M233 -> 234576534 | F32: FANIL | G32: Note 3.2.1.a
D33: b. Net GloBE Income or Loss [A] | E33: =+E68 -> 238034398 | F33: NetGlobeIncome | G33: Note 3.2.1.b
D34: c. Income tax expense | E34: =+E42 -> 3457864 | F34: IncomeTaxExpense | G34: Note 3.2.1.c
D35: d. Adjusted Covered Taxes [B] | E35: =+M311 -> 3582188 | F35: AdjustedCoveredTax | G35: Note 3.2.1.d
D36: e. ETR [C]=[B]/[A] | E36: =+E35/E33 -> 0.015049035 | F36: ETRRate | G36: Note 3.2.1.e
D39: 3.2.1.1 Computation of GloBE Income (Loss) of the Jurisdiction
D40: 1. Aggregate FANIL amount after allocations in Articles 3.4 and 3.5 (All CEs in the jurisdiction) | E40: =+M233 -> 234576534 | F40: AdjustedFANIL
D41: 2. Adjustments | E41: Net amount | F41: Adjustments
D42: (a) Net Taxes Expense - Article 3.2.1 (a) | E42: =+M235 -> 3457864 | F42: GIR2001 | G42: Note 3.2.1.1.2a
D43: (b) Excluded Dividends – Article 3.2.1 (b) | E43: =+M236 -> 0 | F43: GIR2002 | G43: Note 3.2.1.1.2b
D44: (c) Excluded Equity Gain or Loss – Article 3.2.1 (c) | E44: =+M237 -> 0 | F44: GIR2003 | G44: Note 3.2.1.1.2c
D45: (d) Included Revaluation Method Gain or Loss – Article 3.2.1 (d) | E45: =+M238 -> 0 | F45: GIR2004 | G45: Note 3.2.1.1.2d
D46: (e) Gain or loss from disposition of assets and liabilities excluded under Article 6.3 – Article 3.2.1 (e) | E46: =+M239 -> 0 | F46: GIR2005 | G46: Note 3.2.1.1.2e
D47: (f) Asymmetric Foreign Currency Gains or Losses – Article 3.2.1 (f) | E47: =+M240 -> 0 | F47: GIR2006 | G47: Note 3.2.1.1.2f
D48: (g) Policy Disallowed Expenses – Article 3.2.1 (g) | E48: =+M241 -> 0 | F48: GIR2007 | G48: Note 3.2.1.1.2g
D49: (h) Prior Period Errors – Article 3.2.1 (h) | E49: =+M242 -> 0 | F49: GIR2008 | G49: Note 3.2.1.1.2h
D50: (i) Changes in Accounting Principles – Article 3.2.1(h) | E50: =+M243 -> 0 | F50: GIR2009 | G50: Note 3.2.1.1.2i
D51: (j) Accrued Pension Expense – Article 3.2.1 (i) | E51: =+M244 -> 0 | F51: GIR2010 | G51: Note 3.2.1.1.2j
D52: (k) Debt releases - Article 3.2.1 | E52: =+M245 -> 0 | F52: GIR2011 | G52: Note 3.2.1.1.2k
D53: (l) Stock-based compensation – Article 3.2.2 | E53: =+M246 -> 0 | F53: GIR2012 | G53: Note 3.2.1.1.2l
... D68: 3. Net GloBE Income (Loss) of the Jurisdiction | E68: =+M261 -> 238034398 | F68: NetGlobeIncome | G68: Note 3.2.1.1.3
D71: 3.2.1.2 Computation of Adjusted Covered Taxes
D72: (a) Total amount of Adjusted Covered Taxes
D73: 1. Aggregate Current tax expense with respect to Covered Taxes after allocations in Article 4.3 (All CEs in the jurisdiction) | E73: =+M292 -> 3457864 | F73: AggregrateCurrentTax | G73: Note 3.2.1.2.a.1
D74: 2. Adjustments | E74: Net amount | F74: Adjustments
D75: (a) Covered Tax accrued as an expense in the profit before taxation in the financial accounts - Article 4.1.2 (a) | E75: =+M294 -> 0 | F75: GIR2401 | G75: GIR2701 | H75: Note 3.2.1.2.a.2.a
D76: (b) GloBE Loss Deferred Tax Asset established under Article 4.5.1 or used – Article 4.1.2 (b) combined with Article 4.5.3 | E76: 0 | G76: GIR2702 | H76: Note 3.2.1.2.a.2.b | I76: Article 4.5 provides an elective rule to effectively carry GloBE losses forward with a deemed deferred tax asset. When elected, Article 4.5 applies in lieu of the Article 4.4 modified deferred tax accounting rules. Accordingly, Article 4.5 is generally expected to be of greatest utility as a simplification in jurisdictions that do not impose a corporate income tax or impose one at a very low rate given that when the election is made, Article 4.4 no longer applies and temporary differences may result in Top-up Tax.
D77: (c) Covered Taxes for uncertain tax position recorded as a reduction to Covered Taxes in prior year – Article 4.1.2 (c) | E77: =+M295 -> 0 | F77: GIR2402 | G77: GIR2703 | H77: Note 3.2.1.2.a.2.c
D78: (d) Qualified Refundable Tax Credit or Marketable Transferable Tax Credits recorded as a reduction to current tax expense – Article 4.1.2 (d) | E78: =+M296 -> 0 | F78: GIR2403 | G78: GIR2704 | H78: Note 3.2.1.2.a.2.d
D79: (e) Qualified Flow-through Tax Benefits of Qualified Ownership Interests – Article 3.2.1 (c) | E79: =+M297 -> 0 | F79: GIR2404 | G79: GIR2705 | H79: Note 3.2.1.2.a.2.e
D80: (f) Current tax expense on income excluded from GloBE Income or Loss – Article 4.1.3 (a) | E80: =+M298 -> 0 | F80: GIR2405 | G80: GIR2706 | H80: Note 3.2.1.2.a.2.f
D81: (g) Non-Qualified Refundable Tax Credit, Non-Marketable Transferable Tax Credit or Other Tax Credits not recorded as a reduction to current tax expense – Article 4.1.3 (b) | E81: =+M299 -> 0 | F81: GIR2406 | G81: GIR2707 | H81: Note 3.2.1.2.a.2.g
D82: (h) Covered Taxes refunded or credited (except for any Qualified Refundable Tax Credit, or Marketable Transferable Tax Credits) not treated as an adjustment to current tax expense – Article 4.1.3 (c) | E82: =+M300 -> 0 | F82: GIR2407 | G82: GIR2708 | H82: Note 3.2.1.2.a.2.h
D83: (i) Current tax expense related to uncertain tax position– Article 4.1.3 (d) | E83: =+M301 -> 0 | F83: GIR2408 | G83: GIR2709 | H83: Note 3.2.1.2.a.2.i
D84: (j) Current tax expense not expected to be paid within three years – Article 4.1.3 (e) | E84: =+M302 -> 0 | F84: GIR2409 | G84: GIR2710 | H84: Note 3.2.1.2.a.2.j
D85: (k) Post-filing adjustments – Article 4.6.1 | E85: =+M303 -> 0 | F85: GIR2410 | G85: GIR2711 | H85: Note 3.2.1.2.a.2.k
D86: (l) Covered Taxes relating to Net Asset Gain or Net Asset Loss – Article 3.2.6 | E86: =+M304 -> 0 | F86: GIR2411 | G86: GIR2712 | H86: Note 3.2.1.2.a.2.l
D87: (m) Reduction of Covered Taxes of the UPE that is a Flow-through Entity – Article 7.1 | E87: =+M305 -> 0 | F87: GIR2412 | G87: GIR2713 | H87: Note 3.2.1.2.a.2.m
D88: (m) Covered Taxes for GloBE Income of the UPE that is reduced under a Deductible Dividend Regime – Article 7.2.2 | E88: =+M306 -> 0 | F88: GIR2413 | G88: GIR2714 | H88: Note 3.2.1.2.a.2.n
... D92: (r) Increase or decrease in Covered Taxes recorded in equity or Other Comprehensive Income relating to amounts included in GloBE Income or Loss that will be subject to tax under local tax rules – Article 4.1.1 (c) | E92: =+M310 -> 0 | F92: GIR2417 | G92: GIR2718 | H92: Note 3.2.1.2.a.2.r
D93: (s) Excess Negative Tax Expense Carry Forward generated – Article 4.1.5 and 5.2.1 | E93: =+E102 -> 0 | F93: GeneratedInRFY | G93: GIR2719 | H93: Note 3.2.1.2.a.2.s
D94: (t) Decrease in Covered Taxes (but not below zero) by the remaining balance of the Excess Negative Tax Expense Carry-forward – Article 4.1.5 and 5.2.1 | E94: =+E101 -> 0 | F94: UtilizedInRFY | G94: GIR2720 | H94: Note 3.2.1.2.a.2.t
D95: 3. Adjusted Covered Taxes | E95: =E73+SUM(E75:E94) -> 3582188 | G95: AdjustedCoveredTax
D98: (b) Excess Negative Tax Expense Carry-forward | E98: not applicable | F98: ExcessNegTaxExpense | H98: In a Fiscal Year in which there is no Net GloBE Income for a jurisdiction, if the AdjustedCovered Taxes for a jurisdiction are less than zero and less than the Expected Adjusted CoveredTaxes Amount the Constituent Entities in that jurisdiction shall be treated as having AdditionalCurrent Top-up Tax for the jurisdiction under Article 5.4 arising in the current Fiscal Year equal tothe difference between these amounts. The Expected Adjusted Covered Taxes Amount is equal to the GloBE Income or Loss for a jurisdiction multiplied by the Minimum Rate.
D99: 1. Balance from prior years [A] | E99: 0 | F99: PriorYearBalance | G99: Note 3.2.1.2.b.1
D100: 2. Excess Negative Tax Expense Carry-forward generated in the reporting fiscal year [B] | E100: 0 | F100: GeneratedInRFY | G100: Note 3.2.1.2.b.2
D101: 3. Excess Negative Tax Expense Carry-forward utilized for the reporting fiscal year [C] | E101: 0 | F101: UtilizedInRFY | G101: Note 3.2.1.2.b.3
D102: 4. Excess Negative Tax Expense Carry-forward remaining for subsequent years [D]=[A]+[B]-[C] | E102: =+E99+E100+E101 -> 0 | F102: Remaining | G102: Note 3.2.1.2.b.4
D105: (c) Transitional Blended CFC Regime calculation (if any)
D106: 1. CFC Jurisdictions | E106: 2. Subgroup | F106: 3. Aggregated taxes allocated to that subgroup under a Blended CFC Tax Regime | G106: Note 3.2.1.2.c / Note 3.2.1.2.c.1 / Note 3.2.1.2.c.2 / Note 3.2.1.2.c.3
D107: Please indicate the CFC Jurisdiction if applicable | E107: Please indicate Subgroup if applicable | F107: 0
D108: Please indicate the CFC Jurisdiction if applicable | E108: Please indicate Subgroup if applicable | F108: 0
D109: Total | F109: =+F107+F108 -> 0
D112: 3.2.2 Jurisdictional computations relating to deferred tax accounting | E112: applicable
D113: 3.2.2.1 Deferred Tax adjustments
D114: (a) High-level summary
D115: a. Deferred tax expense in the financial accounts [A] | E115: 1. Deferred tax expense for GloBE purposes before recasting and adjustments | F115: =+M325 -> 124324 | G115: DefTaxAmt | H115: Note 3.2.2.1.a.1.a
D116: b. Deferred tax expense in relation to assets or liabilities for which the GloBE carrying value is different to the accounting carrying value [B] | F116: 0 | G116: DiffCarryValue | H116: Note 3.2.2.1.a.1.b
D117: c. Deferred tax expense based on the GloBE carrying value of assets or liabilities [C] | F117: 0 | G117: GloBEValue | H117: Note 3.2.2.1.a.1.c
D118: d. Deferred tax expense for GloBE purposes before recasting and adjustments [D]=[A]-[B]+[C] | F118: =F115-F116+F117 -> 124324 | G118: BefRecastAdjust | H118: Note 3.2.2.1.a.1.d
D119: 2. Total amount of adjustments [E] | F119: =+E144 -> 0 | G119: TotalAdjust | H119: Note 3.2.2.1.a.2
D120: e. Deferred Tax expense for GloBE purposes before recasting [F]=[D]+[E] | E120: 3. Recasting the deferred tax expense to the Minimum Rate | F120: =+F119+F118 -> 124324 | G120: PreRecast | H120: Note 3.2.2.1.a.3.e
D121: f. Difference between deferred tax expense recorded at a lower tax rate than the Minimum Rate and recast at Minimum Rate [G] | F121: =+M344 -> 0 | G121: Higher | H121: Note 3.2.2.1.a.3.f
D122: g. Difference between the deferred tax expense recorded at a higher tax rate than the Minimum Rate and recast at Minimum Rate [H] | F122: =+M345 -> 0 | G122: Lower | H122: Note 3.2.2.1.a.3.g
D123: 4. Total Deferred Tax Adjustment Amount [I]=[F]+[G]-[H] | F123: =+F120+F121-F122 -> 124324 | G123: DeferTaxAdjustAmt | H123: Note 3.2.2.1.a.4
D126: (b) Breakdown of the adjustments
D127: 1. Adjustments to deferred tax expense | E127: Net amount | F127: AdjustmentItem | G127: Note 3.2.2.1.b
D128: (a) Deferred tax expense related to items excluded from GloBE Income or Loss – Article 4.4.1 (a) | E128: =+M327 -> 0 | F128: GIR2501 | G128: Note 3.2.2.1.b.1.a
D129: (b) Deferred tax expense related to Disallowed Accruals– Article 4.4.1 (b) | E129: =+M328 -> 0 | F129: GIR2502 | G129: Note 3.2.2.1.b.1.b
D130: (c) Deferred tax expense related to Unclaimed Accruals – Article 4.4.1 (b) | E130: =+M329 -> 0 | F130: GIR2503 | G130: Note 3.2.2.1.b.1.c
D131: (d) Valuation adjustment or accounting recognition adjustment related to a deferred tax asset – Article 4.4.1 (c) | E131: =+M330 -> 0 | F131: GIR2504 | G131: Note 3.2.2.1.b.1.d
D132: (e) Deferred tax expense arising from a re-measurement related to changes in the tax rate – Article 4.4.1 (d) | E132: =+M331 -> 0 | F132: GIR2505 | G132: Note 3.2.2.1.b.1.e
D133: (f) Deferred tax expense related to the generation and use of tax credits – Article 4.4.1 (e) | E133: =+M332 -> 0 | F133: GIR2506 | G133: Note 3.2.2.1.b.1.f
D134: (g) Substitute Loss Carry Forward DTA or deemed Substitute Loss Carry Forward DTA – Article 4.4.1 (e) | E134: =+M333 -> 0 | F134: GIR2507 | G134: Note 3.2.2.1.b.1.g
...

Sheet 3 GloBE Computations DE
D2: 3 GloBE Computations
D3: The Filing Constituent Entity shall complete Section 3 on a jurisdictional basis, for each jurisdiction (or subgroup, where relevant) where exceptions to the GloBE computation do not apply
D5: Please make sure that only the yellow marked cells are populated. Don't include or delete any other cell, row or column! | E5: To be populated
D6: References to GloBE Information Return (Pillar Two) XML Schema User Guide for Tax Administrations are in light clue | E6: XML references
D7: Further explanations are in light green | E7: Further explanations
D9: 3.1 Characteristics of the jurisdiction (Information purpose only)
D10: 1. Name of the jurisdiction | E10: Germany
D11: 2. Type of subgroup (if any) - mention "n/a" if no subgroup exists | E11: n/a
D12: 3. Identification of subgroup (if any) for the ETR and Top-up Tax computation - mention "n/a" if no subgroup exists | E12: n/a
D13: 4. Jurisdictions with taxing rights | E13: Germany
D14: 5. ETR | E14: =+E36 -> 0.014526739
D15: 6. Adjusted Covered Taxes | E15: =+E35 -> 3803650
D16: 7. Net GloBE Income or Loss | E16: =+E33 -> 261837837
D17: 8. Substance-based Income Exclusion | E17: =+E437 -> 682800
D18: 9. Additional Current Top-up Tax | E18: =+E475 -> 0
D19: 10.Top-up Tax amount under domestic legislation | E19: =+E425 -> 35379524
D20: 11. Elections
D21: 12. Aggregate current tax expense with respect to Covered Taxes after allocations in Article 4.3 | E21: =+E73 -> 3803650
D22: 13. Qualified Refundable Tax Credits or Marketable Transferable Tax Credits (tax expense) | E22: =+E78 -> 0
D23: 14. Other tax credits (tax expense) | E23: =+E81 -> 0
D24: 15. Deferred tax expense amount | E24: =+F123 -> 125558
D25: 16. Qualified Refundable Tax Credits or Marketable Transferable Tax Credits (income) | E25: =+E55 -> 0
D26: 17. Excess Negative Tax Expense Carry Forward | E26: =E93 -> 0
D27: 18. Transition Rules
D30: 3.2 ETR computation | E30: applicable
D31: 3.2.1 ETR | E31: applicable | F31: OverallComputation
D32: a. Financial Accounting Net Income or Loss | E32: =+M233 -> 258034187 | F32: FANIL | G32: Note 3.2.1.a
D33: b. Net GloBE Income or Loss [A] | E33: =+E68 -> 261837837 | F33: NetGlobeIncome | G33: Note 3.2.1.b
D34: c. Income tax expense | E34: =+E42 -> 3803650 | F34: IncomeTaxExpense | G34: Note 3.2.1.c
D35: d. Adjusted Covered Taxes [B] | E35: =+M311 -> 3803650 | F35: AdjustedCoveredTax | G35: Note 3.2.1.d
D36: e. ETR [C]=[B]/[A] | E36: =+E35/E33 -> 0.014526739 | F36: ETRRate | G36: Note 3.2.1.e
D39: 3.2.1.1 Computation of GloBE Income (Loss) of the Jurisdiction
D40: 1. Aggregate FANIL amount after allocations in Articles 3.4 and 3.5 (All CEs in the jurisdiction) | E40: =+M233 -> 258034187 | F40: AdjustedFANIL
D41: 2. Adjustments | E41: Net amount | F41: Adjustments
D42: (a) Net Taxes Expense - Article 3.2.1 (a) | E42: =+M235 -> 3803650 | F42: GIR2001 | G42: Note 3.2.1.1.2a
D43: (b) Excluded Dividends – Article 3.2.1 (b) | E43: =+M236 -> 0 | F43: GIR2002 | G43: Note 3.2.1.1.2b
D44: (c) Excluded Equity Gain or Loss – Article 3.2.1 (c) | E44: =+M237 -> 0 | F44: GIR2003 | G44: Note 3.2.1.1.2c
D45: (d) Included Revaluation Method Gain or Loss – Article 3.2.1 (d) | E45: =+M238 -> 0 | F45: GIR2004 | G45: Note 3.2.1.1.2d
D46: (e) Gain or loss from disposition of assets and liabilities excluded under Article 6.3 – Article 3.2.1 (e) | E46: =+M239 -> 0 | F46: GIR2005 | G46: Note 3.2.1.1.2e
D47: (f) Asymmetric Foreign Currency Gains or Losses – Article 3.2.1 (f) | E47: =+M240 -> 0 | F47: GIR2006 | G47: Note 3.2.1.1.2f
D48: (g) Policy Disallowed Expenses – Article 3.2.1 (g) | E48: =+M241 -> 0 | F48: GIR2007 | G48: Note 3.2.1.1.2g
D49: (h) Prior Period Errors – Article 3.2.1 (h) | E49: =+M242 -> 0 | F49: GIR2008 | G49: Note 3.2.1.1.2h
D50: (i) Changes in Accounting Principles – Article 3.2.1(h) | E50: =+M243 -> 0 | F50: GIR2009 | G50: Note 3.2.1.1.2i
D51: (j) Accrued Pension Expense – Article 3.2.1 (i) | E51: =+M244 -> 0 | F51: GIR2010 | G51: Note 3.2.1.1.2j
D52: (k) Debt releases - Article 3.2.1 | E52: =+M245 -> 0 | F52: GIR2011 | G52: Note 3.2.1.1.2k
D53: (l) Stock-based compensation – Article 3.2.2 | E53: =+M246 -> 0 | F53: GIR2012 | G53: Note 3.2.1.1.2l
... D68: 3. Net GloBE Income (Loss) of the Jurisdiction | E68: =+M261 -> 261837837 | F68: NetGlobeIncome | G68: Note 3.2.1.1.3
D71: 3.2.1.2 Computation of Adjusted Covered Taxes
D72: (a) Total amount of Adjusted Covered Taxes
D73: 1. Aggregate Current tax expense with respect to Covered Taxes after allocations in Article 4.3 (All CEs in the jurisdiction) | E73: =+M292 -> 3803650 | F73: AggregrateCurrentTax | G73: Note 3.2.1.2.a.1
D74: 2. Adjustments | E74: Net amount | F74: Adjustments
D75: (a) Covered Tax accrued as an expense in the profit before taxation in the financial accounts - Article 4.1.2 (a) | E75: =+M294 -> 0 | F75: GIR2401 | G75: GIR2701 | H75: Note 3.2.1.2.a.2.a
D76: (b) GloBE Loss Deferred Tax Asset established under Article 4.5.1 or used – Article 4.1.2 (b) combined with Article 4.5.3 | E76: 0 | G76: GIR2702 | H76: Note 3.2.1.2.a.2.b | I76: Article 4.5 provides an elective rule to effectively carry GloBE losses forward with a deemed deferred tax asset. When elected, Article 4.5 applies in lieu of the Article 4.4 modified deferred tax accounting rules. Accordingly, Article 4.5 is generally expected to be of greatest utility as a simplification in jurisdictions that do not impose a corporate income tax or impose one at a very low rate given that when the election is made, Article 4.4 no longer applies and temporary differences may result in Top-up Tax.
D77: (c) Covered Taxes for uncertain tax position recorded as a reduction to Covered Taxes in prior year – Article 4.1.2 (c) | E77: =+M295 -> 0 | F77: GIR2402 | G77: GIR2703 | H77: Note 3.2.1.2.a.2.c
D78: (d) Qualified Refundable Tax Credit or Marketable Transferable Tax Credits recorded as a reduction to current tax expense – Article 4.1.2 (d) | E78: =+M296 -> 0 | F78: GIR2403 | G78: GIR2704 | H78: Note 3.2.1.2.a.2.d
D79: (e) Qualified Flow-through Tax Benefits of Qualified Ownership Interests – Article 3.2.1 (c) | E79: =+M297 -> 0 | F79: GIR2404 | G79: GIR2705 | H79: Note 3.2.1.2.a.2.e
D80: (f) Current tax expense on income excluded from GloBE Income or Loss – Article 4.1.3 (a) | E80: =+M298 -> 0 | F80: GIR2405 | G80: GIR2706 | H80: Note 3.2.1.2.a.2.f
D81: (g) Non-Qualified Refundable Tax Credit, Non-Marketable Transferable Tax Credit or Other Tax Credits not recorded as a reduction to current tax expense – Article 4.1.3 (b) | E81: =+M299 -> 0 | F81: GIR2406 | G81: GIR2707 | H81: Note 3.2.1.2.a.2.g
D82: (h) Covered Taxes refunded or credited (except for any Qualified Refundable Tax Credit, or Marketable Transferable Tax Credits) not treated as an adjustment to current tax expense – Article 4.1.3 (c) | E82: =+M300 -> 0 | F82: GIR2407 | G82: GIR2708 | H82: Note 3.2.1.2.a.2.h
D83: (i) Current tax expense related to uncertain tax position– Article 4.1.3 (d) | E83: =+M301 -> 0 | F83: GIR2408 | G83: GIR2709 | H83: Note 3.2.1.2.a.2.i
D84: (j) Current tax expense not expected to be paid within three years – Article 4.1.3 (e) | E84: =+M302 -> 0 | F84: GIR2409 | G84: GIR2710 | H84: Note 3.2.1.2.a.2.j
D85: (k) Post-filing adjustments – Article 4.6.1 | E85: =+M303 -> 0 | F85: GIR2410 | G85: GIR2711 | H85: Note 3.2.1.2.a.2.k
D86: (l) Covered Taxes relating to Net Asset Gain or Net Asset Loss – Article 3.2.6 | E86: =+M304 -> 0 | F86: GIR2411 | G86: GIR2712 | H86: Note 3.2.1.2.a.2.l
D87: (m) Reduction of Covered Taxes of the UPE that is a Flow-through Entity – Article 7.1 | E87: =+M305 -> 0 | F87: GIR2412 | G87: GIR2713 | H87: Note 3.2.1.2.a.2.m
D88: (m) Covered Taxes for GloBE Income of the UPE that is reduced under a Deductible Dividend Regime – Article 7.2.2 | E88: =+M306 -> 0 | F88: GIR2413 | G88: GIR2714 | H88: Note 3.2.1.2.a.2.n
... D92: (r) Increase or decrease in Covered Taxes recorded in equity or Other Comprehensive Income relating to amounts included in GloBE Income or Loss that will be subject to tax under local tax rules – Article 4.1.1 (c) | E92: =+M310 -> 0 | F92: GIR2417 | G92: GIR2718 | H92: Note 3.2.1.2.a.2.r
D93: (s) Excess Negative Tax Expense Carry Forward generated – Article 4.1.5 and 5.2.1 | E93: =+E102 -> 0 | F93: GeneratedInRFY | G93: GIR2719 | H93: Note 3.2.1.2.a.2.s
D94: (t) Decrease in Covered Taxes (but not below zero) by the remaining balance of the Excess Negative Tax Expense Carry-forward – Article 4.1.5 and 5.2.1 | E94: =+E101 -> 0 | F94: UtilizedInRFY | G94: GIR2720 | H94: Note 3.2.1.2.a.2.t
D95: 3. Adjusted Covered Taxes | E95: =E73+SUM(E75:E94) -> 3803650 | G95: AdjustedCoveredTax
D98: (b) Excess Negative Tax Expense Carry-forward | E98: not applicable | F98: ExcessNegTaxExpense | H98: In a Fiscal Year in which there is no Net GloBE Income for a jurisdiction, if the AdjustedCovered Taxes for a jurisdiction are less than zero and less than the Expected Adjusted CoveredTaxes Amount the Constituent Entities in that jurisdiction shall be treated as having AdditionalCurrent Top-up Tax for the jurisdiction under Article 5.4 arising in the current Fiscal Year equal tothe difference between these amounts. The Expected Adjusted Covered Taxes Amount is equal to the GloBE Income or Loss for a jurisdiction multiplied by the Minimum Rate.
D99: 1. Balance from prior years [A] | E99: 0 | F99: PriorYearBalance | G99: Note 3.2.1.2.b.1
D100: 2. Excess Negative Tax Expense Carry-forward generated in the reporting fiscal year [B] | E100: 0 | F100: GeneratedInRFY | G100: Note 3.2.1.2.b.2
D101: 3. Excess Negative Tax Expense Carry-forward utilized for the reporting fiscal year [C] | E101: 0 | F101: UtilizedInRFY | G101: Note 3.2.1.2.b.3
D102: 4. Excess Negative Tax Expense Carry-forward remaining for subsequent years [D]=[A]+[B]-[C] | E102: =+E99+E100+E101 -> 0 | F102: Remaining | G102: Note 3.2.1.2.b.4
D105: (c) Transitional Blended CFC Regime calculation (if any)
D106: 1. CFC Jurisdictions | E106: 2. Subgroup | F106: 3. Aggregated taxes allocated to that subgroup under a Blended CFC Tax Regime | G106: Note 3.2.1.2.c / Note 3.2.1.2.c.1 / Note 3.2.1.2.c.2 / Note 3.2.1.2.c.3
D107: Please indicate the CFC Jurisdiction if applicable | E107: Please indicate Subgroup if applicable | F107: 0
D108: Please indicate the CFC Jurisdiction if applicable | E108: Please indicate Subgroup if applicable | F108: 0
D109: Total | F109: =+F107+F108 -> 0
D112: 3.2.2 Jurisdictional computations relating to deferred tax accounting | E112: applicable
D113: 3.2.2.1 Deferred Tax adjustments
D114: (a) High-level summary
D115: a. Deferred tax expense in the financial accounts [A] | E115: 1. Deferred tax expense for GloBE purposes before recasting and adjustments | F115: =+M325 -> 125558 | G115: DefTaxAmt | H115: Note 3.2.2.1.a.1.a
D116: b. Deferred tax expense in relation to assets or liabilities for which the GloBE carrying value is different to the accounting carrying value [B] | F116: 0 | G116: DiffCarryValue | H116: Note 3.2.2.1.a.1.b
D117: c. Deferred tax expense based on the GloBE carrying value of assets or liabilities [C] | F117: 0 | G117: GloBEValue | H117: Note 3.2.2.1.a.1.c
D118: d. Deferred tax expense for GloBE purposes before recasting and adjustments [D]=[A]-[B]+[C] | F118: =F115-F116+F117 -> 125558 | G118: BefRecastAdjust | H118: Note 3.2.2.1.a.1.d
D119: 2. Total amount of adjustments [E] | F119: =+E144 -> 0 | G119: TotalAdjust | H119: Note 3.2.2.1.a.2
D120: e. Deferred Tax expense for GloBE purposes before recasting [F]=[D]+[E] | E120: 3. Recasting the deferred tax expense to the Minimum Rate | F120: =+F119+F118 -> 125558 | G120: PreRecast | H120: Note 3.2.2.1.a.3.e
D121: f. Difference between deferred tax expense recorded at a lower tax rate than the Minimum Rate and recast at Minimum Rate [G] | F121: =+M344 -> 0 | G121: Higher | H121: Note 3.2.2.1.a.3.f
D122: g. Difference between the deferred tax expense recorded at a higher tax rate than the Minimum Rate and recast at Minimum Rate [H] | F122: =+M345 -> 0 | G122: Lower | H122: Note 3.2.2.1.a.3.g
D123: 4. Total Deferred Tax Adjustment Amount [I]=[F]+[G]-[H] | F123: =+F120+F121-F122 -> 125558 | G123: DeferTaxAdjustAmt | H123: Note 3.2.2.1.a.4
D126: (b) Breakdown of the adjustments
D127: 1. Adjustments to deferred tax expense | E127: Net amount | F127: AdjustmentItem | G127: Note 3.2.2.1.b
D128: (a) Deferred tax expense related to items excluded from GloBE Income or Loss – Article 4.4.1 (a) | E128: =+M327 -> 0 | F128: GIR2501 | G128: Note 3.2.2.1.b.1.a
D129: (b) Deferred tax expense related to Disallowed Accruals– Article 4.4.1 (b) | E129: =+M328 -> 0 | F129: GIR2502 | G129: Note 3.2.2.1.b.1.b
D130: (c) Deferred tax expense related to Unclaimed Accruals – Article 4.4.1 (b) | E130: =+M329 -> 0 | F130: GIR2503 | G130: Note 3.2.2.1.b.1.c
D131: (d) Valuation adjustment or accounting recognition adjustment related to a deferred tax asset – Article 4.4.1 (c) | E131: =+M330 -> 0 | F131: GIR2504 | G131: Note 3.2.2.1.b.1.d
D132: (e) Deferred tax expense arising from a re-measurement related to changes in the tax rate – Article 4.4.1 (d) | E132: =+M331 -> 0 | F132: GIR2505 | G132: Note 3.2.2.1.b.1.e
D133: (f) Deferred tax expense related to the generation and use of tax credits – Article 4.4.1 (e) | E133: =+M332 -> 0 | F133: GIR2506 | G133: Note 3.2.2.1.b.1.f
D134: (g) Substitute Loss Carry Forward DTA or deemed Substitute Loss Carry Forward DTA – Article 4.4.1 (e) | E134: =+M333 -> 0 | F134: GIR2507 | G134: Note 3.2.2.1.b.1.g
...

Sheet 3 GloBE Computations RU
D2: 3 GloBE Computations
D3: The Filing Constituent Entity shall complete Section 3 on a jurisdictional basis, for each jurisdiction (or subgroup, where relevant) where exceptions to the GloBE computation do not apply
D5: Please make sure that only the yellow marked cells are populated. Don't include or delete any other cell, row or column! | E5: To be populated
D6: References to GloBE Information Return (Pillar Two) XML Schema User Guide for Tax Administrations are in light clue | E6: XML references
D7: Further explanations are in light green | E7: Further explanations
D9: 3.1 Characteristics of the jurisdiction (Information purpose only)
D10: 1. Name of the jurisdiction | E10: Russia
D11: 2. Type of subgroup (if any) - mention "n/a" if no subgroup exists | E11: n/a
D12: 3. Identification of subgroup (if any) for the ETR and Top-up Tax computation - mention "n/a" if no subgroup exists | E12: n/a
D13: 4. Jurisdictions with taxing rights | E13: Switzerland
D14: 5. ETR | E14: =+E36 -> 0.49998934
D15: 6. Adjusted Covered Taxes | E15: =+E35 -> 23456
D16: 7. Net GloBE Income or Loss | E16: =+E33 -> 46913
D17: 8. Substance-based Income Exclusion | E17: =+E437 -> 341400
D18: 9. Additional Current Top-up Tax | E18: =+E475 -> 0
D19: 10.Top-up Tax amount under domestic legislation | E19: =+E425 -> 0
D20: 11. Elections
D21: 12. Aggregate current tax expense with respect to Covered Taxes after allocations in Article 4.3 | E21: =+E73 -> 23456
D22: 13. Qualified Refundable Tax Credits or Marketable Transferable Tax Credits (tax expense) | E22: =+E78 -> 0
D23: 14. Other tax credits (tax expense) | E23: =+E81 -> 0
D24: 15. Deferred tax expense amount | E24: =+F123 -> 65443
D25: 16. Qualified Refundable Tax Credits or Marketable Transferable Tax Credits (income) | E25: =+E55 -> 0
D26: 17. Excess Negative Tax Expense Carry Forward | E26: =E93 -> 0
D27: 18. Transition Rules
D30: 3.2 ETR computation | E30: applicable
D31: 3.2.1 ETR | E31: applicable | F31: OverallComputation
D32: a. Financial Accounting Net Income or Loss | E32: =+M233 -> 23457 | F32: FANIL | G32: Note 3.2.1.a
D33: b. Net GloBE Income or Loss [A] | E33: =+E68 -> 46913 | F33: NetGlobeIncome | G33: Note 3.2.1.b
D34: c. Income tax expense | E34: =+E42 -> 23456 | F34: IncomeTaxExpense | G34: Note 3.2.1.c
D35: d. Adjusted Covered Taxes [B] | E35: =+M311 -> 23456 | F35: AdjustedCoveredTax | G35: Note 3.2.1.d
D36: e. ETR [C]=[B]/[A] | E36: =+E35/E33 -> 0.49998934 | F36: ETRRate | G36: Note 3.2.1.e
D39: 3.2.1.1 Computation of GloBE Income (Loss) of the Jurisdiction
D40: 1. Aggregate FANIL amount after allocations in Articles 3.4 and 3.5 (All CEs in the jurisdiction) | E40: =+M233 -> 23457 | F40: AdjustedFANIL
D41: 2. Adjustments | E41: Net amount | F41: Adjustments
D42: (a) Net Taxes Expense - Article 3.2.1 (a) | E42: =+M235 -> 23456 | F42: GIR2001 | G42: Note 3.2.1.1.2a
D43: (b) Excluded Dividends – Article 3.2.1 (b) | E43: =+M236 -> 0 | F43: GIR2002 | G43: Note 3.2.1.1.2b
D44: (c) Excluded Equity Gain or Loss – Article 3.2.1 (c) | E44: =+M237 -> 0 | F44: GIR2003 | G44: Note 3.2.1.1.2c
D45: (d) Included Revaluation Method Gain or Loss – Article 3.2.1 (d) | E45: =+M238 -> 0 | F45: GIR2004 | G45: Note 3.2.1.1.2d
D46: (e) Gain or loss from disposition of assets and liabilities excluded under Article 6.3 – Article 3.2.1 (e) | E46: =+M239 -> 0 | F46: GIR2005 | G46: Note 3.2.1.1.2e
D47: (f) Asymmetric Foreign Currency Gains or Losses – Article 3.2.1 (f) | E47: =+M240 -> 0 | F47: GIR2006 | G47: Note 3.2.1.1.2f
D48: (g) Policy Disallowed Expenses – Article 3.2.1 (g) | E48: =+M241 -> 0 | F48: GIR2007 | G48: Note 3.2.1.1.2g
D49: (h) Prior Period Errors – Article 3.2.1 (h) | E49: =+M242 -> 0 | F49: GIR2008 | G49: Note 3.2.1.1.2h
D50: (i) Changes in Accounting Principles – Article 3.2.1(h) | E50: =+M243 -> 0 | F50: GIR2009 | G50: Note 3.2.1.1.2i
D51: (j) Accrued Pension Expense – Article 3.2.1 (i) | E51: =+M244 -> 0 | F51: GIR2010 | G51: Note 3.2.1.1.2j
D52: (k) Debt releases - Article 3.2.1 | E52: =+M245 -> 0 | F52: GIR2011 | G52: Note 3.2.1.1.2k
D53: (l) Stock-based compensation – Article 3.2.2 | E53: =+M246 -> 0 | F53: GIR2012 | G53: Note 3.2.1.1.2l
... D68: 3. Net GloBE Income (Loss) of the Jurisdiction | E68: =+M261 -> 46913 | F68: NetGlobeIncome | G68: Note 3.2.1.1.3
D71: 3.2.1.2 Computation of Adjusted Covered Taxes
D72: (a) Total amount of Adjusted Covered Taxes
D73: 1. Aggregate Current tax expense with respect to Covered Taxes after allocations in Article 4.3 (All CEs in the jurisdiction) | E73: =+M292 -> 23456 | F73: AggregrateCurrentTax | G73: Note 3.2.1.2.a.1
D74: 2. Adjustments | E74: Net amount | F74: Adjustments
D75: (a) Covered Tax accrued as an expense in the profit before taxation in the financial accounts - Article 4.1.2 (a) | E75: =+M294 -> 0 | F75: GIR2401 | G75: GIR2701 | H75: Note 3.2.1.2.a.2.a
D76: (b) GloBE Loss Deferred Tax Asset established under Article 4.5.1 or used – Article 4.1.2 (b) combined with Article 4.5.3 | E76: 0 | G76: GIR2702 | H76: Note 3.2.1.2.a.2.b | I76: Article 4.5 provides an elective rule to effectively carry GloBE losses forward with a deemed deferred tax asset. When elected, Article 4.5 applies in lieu of the Article 4.4 modified deferred tax accounting rules. Accordingly, Article 4.5 is generally expected to be of greatest utility as a simplification in jurisdictions that do not impose a corporate income tax or impose one at a very low rate given that when the election is made, Article 4.4 no longer applies and temporary differences may result in Top-up Tax.
D77: (c) Covered Taxes for uncertain tax position recorded as a reduction to Covered Taxes in prior year – Article 4.1.2 (c) | E77: =+M295 -> 0 | F77: GIR2402 | G77: GIR2703 | H77: Note 3.2.1.2.a.2.c
D78: (d) Qualified Refundable Tax Credit or Marketable Transferable Tax Credits recorded as a reduction to current tax expense – Article 4.1.2 (d) | E78: =+M296 -> 0 | F78: GIR2403 | G78: GIR2704 | H78: Note 3.2.1.2.a.2.d
D79: (e) Qualified Flow-through Tax Benefits of Qualified Ownership Interests – Article 3.2.1 (c) | E79: =+M297 -> 0 | F79: GIR2404 | G79: GIR2705 | H79: Note 3.2.1.2.a.2.e
D80: (f) Current tax expense on income excluded from GloBE Income or Loss – Article 4.1.3 (a) | E80: =+M298 -> 0 | F80: GIR2405 | G80: GIR2706 | H80: Note 3.2.1.2.a.2.f
D81: (g) Non-Qualified Refundable Tax Credit, Non-Marketable Transferable Tax Credit or Other Tax Credits not recorded as a reduction to current tax expense – Article 4.1.3 (b) | E81: =+M299 -> 0 | F81: GIR2406 | G81: GIR2707 | H81: Note 3.2.1.2.a.2.g
D82: (h) Covered Taxes refunded or credited (except for any Qualified Refundable Tax Credit, or Marketable Transferable Tax Credits) not treated as an adjustment to current tax expense – Article 4.1.3 (c) | E82: =+M300 -> 0 | F82: GIR2407 | G82: GIR2708 | H82: Note 3.2.1.2.a.2.h
D83: (i) Current tax expense related to uncertain tax position– Article 4.1.3 (d) | E83: =+M301 -> 0 | F83: GIR2408 | G83: GIR2709 | H83: Note 3.2.1.2.a.2.i
D84: (j) Current tax expense not expected to be paid within three years – Article 4.1.3 (e) | E84: =+M302 -> 0 | F84: GIR2409 | G84: GIR2710 | H84: Note 3.2.1.2.a.2.j
D85: (k) Post-filing adjustments – Article 4.6.1 | E85: =+M303 -> 0 | F85: GIR2410 | G85: GIR2711 | H85: Note 3.2.1.2.a.2.k
D86: (l) Covered Taxes relating to Net Asset Gain or Net Asset Loss – Article 3.2.6 | E86: =+M304 -> 0 | F86: GIR2411 | G86: GIR2712 | H86: Note 3.2.1.2.a.2.l
D87: (m) Reduction of Covered Taxes of the UPE that is a Flow-through Entity – Article 7.1 | E87: =+M305 -> 0 | F87: GIR2412 | G87: GIR2713 | H87: Note 3.2.1.2.a.2.m
D88: (m) Covered Taxes for GloBE Income of the UPE that is reduced under a Deductible Dividend Regime – Article 7.2.2 | E88: =+M306 -> 0 | F88: GIR2413 | G88: GIR2714 | H88: Note 3.2.1.2.a.2.n
... D92: (r) Increase or decrease in Covered Taxes recorded in equity or Other Comprehensive Income relating to amounts included in GloBE Income or Loss that will be subject to tax under local tax rules – Article 4.1.1 (c) | E92: =+M310 -> 0 | F92: GIR2417 | G92: GIR2718 | H92: Note 3.2.1.2.a.2.r
D93: (s) Excess Negative Tax Expense Carry Forward generated – Article 4.1.5 and 5.2.1 | E93: =+E102 -> 0 | F93: GeneratedInRFY | G93: GIR2719 | H93: Note 3.2.1.2.a.2.s
D94: (t) Decrease in Covered Taxes (but not below zero) by the remaining balance of the Excess Negative Tax Expense Carry-forward – Article 4.1.5 and 5.2.1 | E94: =+E101 -> 0 | F94: UtilizedInRFY | G94: GIR2720 | H94: Note 3.2.1.2.a.2.t
D95: 3. Adjusted Covered Taxes | E95: =E73+SUM(E75:E94) -> 23456 | G95: AdjustedCoveredTax
D98: (b) Excess Negative Tax Expense Carry-forward | E98: not applicable | F98: ExcessNegTaxExpense | H98: In a Fiscal Year in which there is no Net GloBE Income for a jurisdiction, if the AdjustedCovered Taxes for a jurisdiction are less than zero and less than the Expected Adjusted CoveredTaxes Amount the Constituent Entities in that jurisdiction shall be treated as having AdditionalCurrent Top-up Tax for the jurisdiction under Article 5.4 arising in the current Fiscal Year equal tothe difference between these amounts. The Expected Adjusted Covered Taxes Amount is equal to the GloBE Income or Loss for a jurisdiction multiplied by the Minimum Rate.
D99: 1. Balance from prior years [A] | E99: 0 | F99: PriorYearBalance | G99: Note 3.2.1.2.b.1
D100: 2. Excess Negative Tax Expense Carry-forward generated in the reporting fiscal year [B] | E100: 0 | F100: GeneratedInRFY | G100: Note 3.2.1.2.b.2
D101: 3. Excess Negative Tax Expense Carry-forward utilized for the reporting fiscal year [C] | E101: 0 | F101: UtilizedInRFY | G101: Note 3.2.1.2.b.3
D102: 4. Excess Negative Tax Expense Carry-forward remaining for subsequent years [D]=[A]+[B]-[C] | E102: =+E99+E100+E101 -> 0 | F102: Remaining | G102: Note 3.2.1.2.b.4
D105: (c) Transitional Blended CFC Regime calculation (if any)
D106: 1. CFC Jurisdictions | E106: 2. Subgroup | F106: 3. Aggregated taxes allocated to that subgroup under a Blended CFC Tax Regime | G106: Note 3.2.1.2.c / Note 3.2.1.2.c.1 / Note 3.2.1.2.c.2 / Note 3.2.1.2.c.3
D107: Please indicate the CFC Jurisdiction if applicable | E107: Please indicate Subgroup if applicable | F107: 0
D108: Please indicate the CFC Jurisdiction if applicable | E108: Please indicate Subgroup if applicable | F108: 0
D109: Total | F109: =+F107+F108 -> 0
D112: 3.2.2 Jurisdictional computations relating to deferred tax accounting | E112: applicable
D113: 3.2.2.1 Deferred Tax adjustments
D114: (a) High-level summary
D115: a. Deferred tax expense in the financial accounts [A] | E115: 1. Deferred tax expense for GloBE purposes before recasting and adjustments | F115: =+M325 -> 65443 | G115: DefTaxAmt | H115: Note 3.2.2.1.a.1.a
D116: b. Deferred tax expense in relation to assets or liabilities for which the GloBE carrying value is different to the accounting carrying value [B] | F116: 0 | G116: DiffCarryValue | H116: Note 3.2.2.1.a.1.b
D117: c. Deferred tax expense based on the GloBE carrying value of assets or liabilities [C] | F117: 0 | G117: GloBEValue | H117: Note 3.2.2.1.a.1.c
D118: d. Deferred tax expense for GloBE purposes before recasting and adjustments [D]=[A]-[B]+[C] | F118: =F115-F116+F117 -> 65443 | G118: BefRecastAdjust | H118: Note 3.2.2.1.a.1.d
D119: 2. Total amount of adjustments [E] | F119: =+E144 -> 0 | G119: TotalAdjust | H119: Note 3.2.2.1.a.2
D120: e. Deferred Tax expense for GloBE purposes before recasting [F]=[D]+[E] | E120: 3. Recasting the deferred tax expense to the Minimum Rate | F120: =+F119+F118 -> 65443 | G120: PreRecast | H120: Note 3.2.2.1.a.3.e
D121: f. Difference between deferred tax expense recorded at a lower tax rate than the Minimum Rate and recast at Minimum Rate [G] | F121: =+M344 -> 0 | G121: Higher | H121: Note 3.2.2.1.a.3.f
D122: g. Difference between the deferred tax expense recorded at a higher tax rate than the Minimum Rate and recast at Minimum Rate [H] | F122: =+M345 -> 0 | G122: Lower | H122: Note 3.2.2.1.a.3.g
D123: 4. Total Deferred Tax Adjustment Amount [I]=[F]+[G]-[H] | F123: =+F120+F121-F122 -> 65443 | G123: DeferTaxAdjustAmt | H123: Note 3.2.2.1.a.4
D126: (b) Breakdown of the adjustments
D127: 1. Adjustments to deferred tax expense | E127: Net amount | F127: AdjustmentItem | G127: Note 3.2.2.1.b
D128: (a) Deferred tax expense related to items excluded from GloBE Income or Loss – Article 4.4.1 (a) | E128: =+M327 -> 0 | F128: GIR2501 | G128: Note 3.2.2.1.b.1.a
D129: (b) Deferred tax expense related to Disallowed Accruals– Article 4.4.1 (b) | E129: =+M328 -> 0 | F129: GIR2502 | G129: Note 3.2.2.1.b.1.b
D130: (c) Deferred tax expense related to Unclaimed Accruals – Article 4.4.1 (b) | E130: =+M329 -> 0 | F130: GIR2503 | G130: Note 3.2.2.1.b.1.c
D131: (d) Valuation adjustment or accounting recognition adjustment related to a deferred tax asset – Article 4.4.1 (c) | E131: =+M330 -> 0 | F131: GIR2504 | G131: Note 3.2.2.1.b.1.d
D132: (e) Deferred tax expense arising from a re-measurement related to changes in the tax rate – Article 4.4.1 (d) | E132: =+M331 -> 0 | F132: GIR2505 | G132: Note 3.2.2.1.b.1.e
D133: (f) Deferred tax expense related to the generation and use of tax credits – Article 4.4.1 (e) | E133: =+M332 -> 0 | F133: GIR2506 | G133: Note 3.2.2.1.b.1.f
D134: (g) Substitute Loss Carry Forward DTA or deemed Substitute Loss Carry Forward DTA – Article 4.4.1 (e) | E134: =+M333 -> 0 | F134: GIR2507 | G134: Note 3.2.2.1.b.1.g
...

Sheet 3 GloBE Computations DK
D2: 3 GloBE Computations
D3: The Filing Constituent Entity shall complete Section 3 on a jurisdictional basis, for each jurisdiction (or subgroup, where relevant) where exceptions to the GloBE computation do not apply
D5: Please make sure that only the yellow marked cells are populated. Don't include or delete any other cell, row or column! | E5: To be populated
D6: References to GloBE Information Return (Pillar Two) XML Schema User Guide for Tax Administrations are in light clue | E6: XML references
D7: Further explanations are in light green | E7: Further explanations
D9: 3.1 Characteristics of the jurisdiction (Information purpose only)
D10: 1. Name of the jurisdiction | E10: Denmark
D11: 2. Type of subgroup (if any) - mention "n/a" if no subgroup exists | E11: n/a
D12: 3. Identification of subgroup (if any) for the ETR and Top-up Tax computation - mention "n/a" if no subgroup exists | E12: n/a
D13: 4. Jurisdictions with taxing rights | E13: Denmark
D14: 5. ETR | E14: =+E36 -> 0.038699763
D15: 6. Adjusted Covered Taxes | E15: =+E35 -> 3456765
D16: 7. Net GloBE Income or Loss | E16: =+E33 -> 89322639
D17: 8. Substance-based Income Exclusion | E17: =+E437 -> 341400
D18: 9. Additional Current Top-up Tax | E18: =+E475 -> 0
D19: 10.Top-up Tax amount under domestic legislation | E19: =+E425 -> 9903632.9
D20: 11. Elections
D21: 12. Aggregate current tax expense with respect to Covered Taxes after allocations in Article 4.3 | E21: =+E73 -> 3456765
D22: 13. Qualified Refundable Tax Credits or Marketable Transferable Tax Credits (tax expense) | E22: =+E78 -> 0
D23: 14. Other tax credits (tax expense) | E23: =+E81 -> 0
D24: 15. Deferred tax expense amount | E24: =+F123 -> 4565
D25: 16. Qualified Refundable Tax Credits or Marketable Transferable Tax Credits (income) | E25: =+E55 -> 0
D26: 17. Excess Negative Tax Expense Carry Forward | E26: =E93 -> 0
D27: 18. Transition Rules
D30: 3.2 ETR computation | E30: applicable
D31: 3.2.1 ETR | E31: applicable | F31: OverallComputation
D32: a. Financial Accounting Net Income or Loss | E32: =+M233 -> 85865874 | F32: FANIL | G32: Note 3.2.1.a
D33: b. Net GloBE Income or Loss [A] | E33: =+E68 -> 89322639 | F33: NetGlobeIncome | G33: Note 3.2.1.b
D34: c. Income tax expense | E34: =+E42 -> 3456765 | F34: IncomeTaxExpense | G34: Note 3.2.1.c
D35: d. Adjusted Covered Taxes [B] | E35: =+M311 -> 3456765 | F35: AdjustedCoveredTax | G35: Note 3.2.1.d
D36: e. ETR [C]=[B]/[A] | E36: =+E35/E33 -> 0.038699763 | F36: ETRRate | G36: Note 3.2.1.e
D39: 3.2.1.1 Computation of GloBE Income (Loss) of the Jurisdiction
D40: 1. Aggregate FANIL amount after allocations in Articles 3.4 and 3.5 (All CEs in the jurisdiction) | E40: =+M233 -> 85865874 | F40: AdjustedFANIL
D41: 2. Adjustments | E41: Net amount | F41: Adjustments
D42: (a) Net Taxes Expense - Article 3.2.1 (a) | E42: =+M235 -> 3456765 | F42: GIR2001 | G42: Note 3.2.1.1.2a
D43: (b) Excluded Dividends – Article 3.2.1 (b) | E43: =+M236 -> 0 | F43: GIR2002 | G43: Note 3.2.1.1.2b
D44: (c) Excluded Equity Gain or Loss – Article 3.2.1 (c) | E44: =+M237 -> 0 | F44: GIR2003 | G44: Note 3.2.1.1.2c
D45: (d) Included Revaluation Method Gain or Loss – Article 3.2.1 (d) | E45: =+M238 -> 0 | F45: GIR2004 | G45: Note 3.2.1.1.2d
D46: (e) Gain or loss from disposition of assets and liabilities excluded under Article 6.3 – Article 3.2.1 (e) | E46: =+M239 -> 0 | F46: GIR2005 | G46: Note 3.2.1.1.2e
D47: (f) Asymmetric Foreign Currency Gains or Losses – Article 3.2.1 (f) | E47: =+M240 -> 0 | F47: GIR2006 | G47: Note 3.2.1.1.2f
D48: (g) Policy Disallowed Expenses – Article 3.2.1 (g) | E48: =+M241 -> 0 | F48: GIR2007 | G48: Note 3.2.1.1.2g
D49: (h) Prior Period Errors – Article 3.2.1 (h) | E49: =+M242 -> 0 | F49: GIR2008 | G49: Note 3.2.1.1.2h
D50: (i) Changes in Accounting Principles – Article 3.2.1(h) | E50: =+M243 -> 0 | F50: GIR2009 | G50: Note 3.2.1.1.2i
D51: (j) Accrued Pension Expense – Article 3.2.1 (i) | E51: =+M244 -> 0 | F51: GIR2010 | G51: Note 3.2.1.1.2j
D52: (k) Debt releases - Article 3.2.1 | E52: =+M245 -> 0 | F52: GIR2011 | G52: Note 3.2.1.1.2k
D53: (l) Stock-based compensation – Article 3.2.2 | E53: =+M246 -> 0 | F53: GIR2012 | G53: Note 3.2.1.1.2l
... D68: 3. Net GloBE Income (Loss) of the Jurisdiction | E68: =+M261 -> 89322639 | F68: NetGlobeIncome | G68: Note 3.2.1.1.3
D71: 3.2.1.2 Computation of Adjusted Covered Taxes
D72: (a) Total amount of Adjusted Covered Taxes
D73: 1. Aggregate Current tax expense with respect to Covered Taxes after allocations in Article 4.3 (All CEs in the jurisdiction) | E73: =+M292 -> 3456765 | F73: AggregrateCurrentTax | G73: Note 3.2.1.2.a.1
D74: 2. Adjustments | E74: Net amount | F74: Adjustments
D75: (a) Covered Tax accrued as an expense in the profit before taxation in the financial accounts - Article 4.1.2 (a) | E75: =+M294 -> 0 | F75: GIR2401 | G75: GIR2701 | H75: Note 3.2.1.2.a.2.a
D76: (b) GloBE Loss Deferred Tax Asset established under Article 4.5.1 or used – Article 4.1.2 (b) combined with Article 4.5.3 | E76: 0 | G76: GIR2702 | H76: Note 3.2.1.2.a.2.b | I76: Article 4.5 provides an elective rule to effectively carry GloBE losses forward with a deemed deferred tax asset. When elected, Article 4.5 applies in lieu of the Article 4.4 modified deferred tax accounting rules. Accordingly, Article 4.5 is generally expected to be of greatest utility as a simplification in jurisdictions that do not impose a corporate income tax or impose one at a very low rate given that when the election is made, Article 4.4 no longer applies and temporary differences may result in Top-up Tax.
D77: (c) Covered Taxes for uncertain tax position recorded as a reduction to Covered Taxes in prior year – Article 4.1.2 (c) | E77: =+M295 -> 0 | F77: GIR2402 | G77: GIR2703 | H77: Note 3.2.1.2.a.2.c
D78: (d) Qualified Refundable Tax Credit or Marketable Transferable Tax Credits recorded as a reduction to current tax expense – Article 4.1.2 (d) | E78: =+M296 -> 0 | F78: GIR2403 | G78: GIR2704 | H78: Note 3.2.1.2.a.2.d
D79: (e) Qualified Flow-through Tax Benefits of Qualified Ownership Interests – Article 3.2.1 (c) | E79: =+M297 -> 0 | F79: GIR2404 | G79: GIR2705 | H79: Note 3.2.1.2.a.2.e
D80: (f) Current tax expense on income excluded from GloBE Income or Loss – Article 4.1.3 (a) | E80: =+M298 -> 0 | F80: GIR2405 | G80: GIR2706 | H80: Note 3.2.1.2.a.2.f
D81: (g) Non-Qualified Refundable Tax Credit, Non-Marketable Transferable Tax Credit or Other Tax Credits not recorded as a reduction to current tax expense – Article 4.1.3 (b) | E81: =+M299 -> 0 | F81: GIR2406 | G81: GIR2707 | H81: Note 3.2.1.2.a.2.g
D82: (h) Covered Taxes refunded or credited (except for any Qualified Refundable Tax Credit, or Marketable Transferable Tax Credits) not treated as an adjustment to current tax expense – Article 4.1.3 (c) | E82: =+M300 -> 0 | F82: GIR2407 | G82: GIR2708 | H82: Note 3.2.1.2.a.2.h
D83: (i) Current tax expense related to uncertain tax position– Article 4.1.3 (d) | E83: =+M301 -> 0 | F83: GIR2408 | G83: GIR2709 | H83: Note 3.2.1.2.a.2.i
D84: (j) Current tax expense not expected to be paid within three years – Article 4.1.3 (e) | E84: =+M302 -> 0 | F84: GIR2409 | G84: GIR2710 | H84: Note 3.2.1.2.a.2.j
D85: (k) Post-filing adjustments – Article 4.6.1 | E85: =+M303 -> 0 | F85: GIR2410 | G85: GIR2711 | H85: Note 3.2.1.2.a.2.k
D86: (l) Covered Taxes relating to Net Asset Gain or Net Asset Loss – Article 3.2.6 | E86: =+M304 -> 0 | F86: GIR2411 | G86: GIR2712 | H86: Note 3.2.1.2.a.2.l
D87: (m) Reduction of Covered Taxes of the UPE that is a Flow-through Entity – Article 7.1 | E87: =+M305 -> 0 | F87: GIR2412 | G87: GIR2713 | H87: Note 3.2.1.2.a.2.m
D88: (m) Covered Taxes for GloBE Income of the UPE that is reduced under a Deductible Dividend Regime – Article 7.2.2 | E88: =+M306 -> 0 | F88: GIR2413 | G88: GIR2714 | H88: Note 3.2.1.2.a.2.n
... D92: (r) Increase or decrease in Covered Taxes recorded in equity or Other Comprehensive Income relating to amounts included in GloBE Income or Loss that will be subject to tax under local tax rules – Article 4.1.1 (c) | E92: =+M310 -> 0 | F92: GIR2417 | G92: GIR2718 | H92: Note 3.2.1.2.a.2.r
D93: (s) Excess Negative Tax Expense Carry Forward generated – Article 4.1.5 and 5.2.1 | E93: =+E102 -> 0 | F93: GeneratedInRFY | G93: GIR2719 | H93: Note 3.2.1.2.a.2.s
D94: (t) Decrease in Covered Taxes (but not below zero) by the remaining balance of the Excess Negative Tax Expense Carry-forward – Article 4.1.5 and 5.2.1 | E94: =+E101 -> 0 | F94: UtilizedInRFY | G94: GIR2720 | H94: Note 3.2.1.2.a.2.t
D95: 3. Adjusted Covered Taxes | E95: =E73+SUM(E75:E94) -> 3456765 | G95: AdjustedCoveredTax
D98: (b) Excess Negative Tax Expense Carry-forward | E98: not applicable | F98: ExcessNegTaxExpense | H98: In a Fiscal Year in which there is no Net GloBE Income for a jurisdiction, if the AdjustedCovered Taxes for a jurisdiction are less than zero and less than the Expected Adjusted CoveredTaxes Amount the Constituent Entities in that jurisdiction shall be treated as having AdditionalCurrent Top-up Tax for the jurisdiction under Article 5.4 arising in the current Fiscal Year equal tothe difference between these amounts. The Expected Adjusted Covered Taxes Amount is equal to the GloBE Income or Loss for a jurisdiction multiplied by the Minimum Rate.
D99: 1. Balance from prior years [A] | E99: 0 | F99: PriorYearBalance | G99: Note 3.2.1.2.b.1
D100: 2. Excess Negative Tax Expense Carry-forward generated in the reporting fiscal year [B] | E100: 0 | F100: GeneratedInRFY | G100: Note 3.2.1.2.b.2
D101: 3. Excess Negative Tax Expense Carry-forward utilized for the reporting fiscal year [C] | E101: 0 | F101: UtilizedInRFY | G101: Note 3.2.1.2.b.3
D102: 4. Excess Negative Tax Expense Carry-forward remaining for subsequent years [D]=[A]+[B]-[C] | E102: =+E99+E100+E101 -> 0 | F102: Remaining | G102: Note 3.2.1.2.b.4
D105: (c) Transitional Blended CFC Regime calculation (if any)
D106: 1. CFC Jurisdictions | E106: 2. Subgroup | F106: 3. Aggregated taxes allocated to that subgroup under a Blended CFC Tax Regime | G106: Note 3.2.1.2.c / Note 3.2.1.2.c.1 / Note 3.2.1.2.c.2 / Note 3.2.1.2.c.3
D107: Please indicate the CFC Jurisdiction if applicable | E107: Please indicate Subgroup if applicable | F107: 0
D108: Please indicate the CFC Jurisdiction if applicable | E108: Please indicate Subgroup if applicable | F108: 0
D109: Total | F109: =+F107+F108 -> 0
D112: 3.2.2 Jurisdictional computations relating to deferred tax accounting | E112: applicable
D113: 3.2.2.1 Deferred Tax adjustments
D114: (a) High-level summary
D115: a. Deferred tax expense in the financial accounts [A] | E115: 1. Deferred tax expense for GloBE purposes before recasting and adjustments | F115: =+M325 -> 4565 | G115: DefTaxAmt | H115: Note 3.2.2.1.a.1.a
D116: b. Deferred tax expense in relation to assets or liabilities for which the GloBE carrying value is different to the accounting carrying value [B] | F116: 0 | G116: DiffCarryValue | H116: Note 3.2.2.1.a.1.b
D117: c. Deferred tax expense based on the GloBE carrying value of assets or liabilities [C] | F117: 0 | G117: GloBEValue | H117: Note 3.2.2.1.a.1.c
D118: d. Deferred tax expense for GloBE purposes before recasting and adjustments [D]=[A]-[B]+[C] | F118: =F115-F116+F117 -> 4565 | G118: BefRecastAdjust | H118: Note 3.2.2.1.a.1.d
D119: 2. Total amount of adjustments [E] | F119: =+E144 -> 0 | G119: TotalAdjust | H119: Note 3.2.2.1.a.2
D120: e. Deferred Tax expense for GloBE purposes before recasting [F]=[D]+[E] | E120: 3. Recasting the deferred tax expense to the Minimum Rate | F120: =+F119+F118 -> 4565 | G120: PreRecast | H120: Note 3.2.2.1.a.3.e
D121: f. Difference between deferred tax expense recorded at a lower tax rate than the Minimum Rate and recast at Minimum Rate [G] | F121: =+M344 -> 0 | G121: Higher | H121: Note 3.2.2.1.a.3.f
D122: g. Difference between the deferred tax expense recorded at a higher tax rate than the Minimum Rate and recast at Minimum Rate [H] | F122: =+M345 -> 0 | G122: Lower | H122: Note 3.2.2.1.a.3.g
D123: 4. Total Deferred Tax Adjustment Amount [I]=[F]+[G]-[H] | F123: =+F120+F121-F122 -> 4565 | G123: DeferTaxAdjustAmt | H123: Note 3.2.2.1.a.4
D126: (b) Breakdown of the adjustments
D127: 1. Adjustments to deferred tax expense | E127: Net amount | F127: AdjustmentItem | G127: Note 3.2.2.1.b
D128: (a) Deferred tax expense related to items excluded from GloBE Income or Loss – Article 4.4.1 (a) | E128: =+M327 -> 0 | F128: GIR2501 | G128: Note 3.2.2.1.b.1.a
D129: (b) Deferred tax expense related to Disallowed Accruals– Article 4.4.1 (b) | E129: =+M328 -> 0 | F129: GIR2502 | G129: Note 3.2.2.1.b.1.b
D130: (c) Deferred tax expense related to Unclaimed Accruals – Article 4.4.1 (b) | E130: =+M329 -> 0 | F130: GIR2503 | G130: Note 3.2.2.1.b.1.c
D131: (d) Valuation adjustment or accounting recognition adjustment related to a deferred tax asset – Article 4.4.1 (c) | E131: =+M330 -> 0 | F131: GIR2504 | G131: Note 3.2.2.1.b.1.d
D132: (e) Deferred tax expense arising from a re-measurement related to changes in the tax rate – Article 4.4.1 (d) | E132: =+M331 -> 0 | F132: GIR2505 | G132: Note 3.2.2.1.b.1.e
D133: (f) Deferred tax expense related to the generation and use of tax credits – Article 4.4.1 (e) | E133: =+M332 -> 0 | F133: GIR2506 | G133: Note 3.2.2.1.b.1.f
D134: (g) Substitute Loss Carry Forward DTA or deemed Substitute Loss Carry Forward DTA – Article 4.4.1 (e) | E134: =+M333 -> 0 | F134: GIR2507 | G134: Note 3.2.2.1.b.1.g
...

Sheet 3 GloBE Computations SE
D2: 3 GloBE Computations
D3: The Filing Constituent Entity shall complete Section 3 on a jurisdictional basis, for each jurisdiction (or subgroup, where relevant) where exceptions to the GloBE computation do not apply
D5: Please make sure that only the yellow marked cells are populated. Don't include or delete any other cell, row or column! | E5: To be populated
D6: References to GloBE Information Return (Pillar Two) XML Schema User Guide for Tax Administrations are in light clue | E6: XML references
D7: Further explanations are in light green | E7: Further explanations
D9: 3.1 Characteristics of the jurisdiction (Information purpose only)
D10: 1. Name of the jurisdiction | E10: Sweden
D11: 2. Type of subgroup (if any) - mention "n/a" if no subgroup exists | E11: n/a
D12: 3. Identification of subgroup (if any) for the ETR and Top-up Tax computation - mention "n/a" if no subgroup exists | E12: n/a
D13: 4. Jurisdictions with taxing rights | E13: Sweden
D14: 5. ETR | E14: =+E36 -> 0.70370381
D15: 6. Adjusted Covered Taxes | E15: =+E35 -> 234567
D16: 7. Net GloBE Income or Loss | E16: =+E33 -> 333332
D17: 8. Substance-based Income Exclusion | E17: =+E437 -> 341400
D18: 9. Additional Current Top-up Tax | E18: =+E475 -> 0
D19: 10.Top-up Tax amount under domestic legislation | E19: =+E425 -> 0
D20: 11. Elections
D21: 12. Aggregate current tax expense with respect to Covered Taxes after allocations in Article 4.3 | E21: =+E73 -> 234567
D22: 13. Qualified Refundable Tax Credits or Marketable Transferable Tax Credits (tax expense) | E22: =+E78 -> 0
D23: 14. Other tax credits (tax expense) | E23: =+E81 -> 0
D24: 15. Deferred tax expense amount | E24: =+F123 -> 3456
D25: 16. Qualified Refundable Tax Credits or Marketable Transferable Tax Credits (income) | E25: =+E55 -> 0
D26: 17. Excess Negative Tax Expense Carry Forward | E26: =E93 -> 0
D27: 18. Transition Rules
D30: 3.2 ETR computation | E30: applicable
D31: 3.2.1 ETR | E31: applicable | F31: OverallComputation
D32: a. Financial Accounting Net Income or Loss | E32: =+M233 -> 98765 | F32: FANIL | G32: Note 3.2.1.a
D33: b. Net GloBE Income or Loss [A] | E33: =+E68 -> 333332 | F33: NetGlobeIncome | G33: Note 3.2.1.b
D34: c. Income tax expense | E34: =+E42 -> 234567 | F34: IncomeTaxExpense | G34: Note 3.2.1.c
D35: d. Adjusted Covered Taxes [B] | E35: =+M311 -> 234567 | F35: AdjustedCoveredTax | G35: Note 3.2.1.d
D36: e. ETR [C]=[B]/[A] | E36: =+E35/E33 -> 0.70370381 | F36: ETRRate | G36: Note 3.2.1.e
D39: 3.2.1.1 Computation of GloBE Income (Loss) of the Jurisdiction
D40: 1. Aggregate FANIL amount after allocations in Articles 3.4 and 3.5 (All CEs in the jurisdiction) | E40: =+M233 -> 98765 | F40: AdjustedFANIL
D41: 2. Adjustments | E41: Net amount | F41: Adjustments
D42: (a) Net Taxes Expense - Article 3.2.1 (a) | E42: =+M235 -> 234567 | F42: GIR2001 | G42: Note 3.2.1.1.2a
D43: (b) Excluded Dividends – Article 3.2.1 (b) | E43: =+M236 -> 0 | F43: GIR2002 | G43: Note 3.2.1.1.2b
D44: (c) Excluded Equity Gain or Loss – Article 3.2.1 (c) | E44: =+M237 -> 0 | F44: GIR2003 | G44: Note 3.2.1.1.2c
D45: (d) Included Revaluation Method Gain or Loss – Article 3.2.1 (d) | E45: =+M238 -> 0 | F45: GIR2004 | G45: Note 3.2.1.1.2d
D46: (e) Gain or loss from disposition of assets and liabilities excluded under Article 6.3 – Article 3.2.1 (e) | E46: =+M239 -> 0 | F46: GIR2005 | G46: Note 3.2.1.1.2e
D47: (f) Asymmetric Foreign Currency Gains or Losses – Article 3.2.1 (f) | E47: =+M240 -> 0 | F47: GIR2006 | G47: Note 3.2.1.1.2f
D48: (g) Policy Disallowed Expenses – Article 3.2.1 (g) | E48: =+M241 -> 0 | F48: GIR2007 | G48: Note 3.2.1.1.2g
D49: (h) Prior Period Errors – Article 3.2.1 (h) | E49: =+M242 -> 0 | F49: GIR2008 | G49: Note 3.2.1.1.2h
D50: (i) Changes in Accounting Principles – Article 3.2.1(h) | E50: =+M243 -> 0 | F50: GIR2009 | G50: Note 3.2.1.1.2i
D51: (j) Accrued Pension Expense – Article 3.2.1 (i) | E51: =+M244 -> 0 | F51: GIR2010 | G51: Note 3.2.1.1.2j
D52: (k) Debt releases - Article 3.2.1 | E52: =+M245 -> 0 | F52: GIR2011 | G52: Note 3.2.1.1.2k
D53: (l) Stock-based compensation – Article 3.2.2 | E53: =+M246 -> 0 | F53: GIR2012 | G53: Note 3.2.1.1.2l
... D68: 3. Net GloBE Income (Loss) of the Jurisdiction | E68: =+M261 -> 333332 | F68: NetGlobeIncome | G68: Note 3.2.1.1.3
D71: 3.2.1.2 Computation of Adjusted Covered Taxes
D72: (a) Total amount of Adjusted Covered Taxes
D73: 1. Aggregate Current tax expense with respect to Covered Taxes after allocations in Article 4.3 (All CEs in the jurisdiction) | E73: =+M292 -> 234567 | F73: AggregrateCurrentTax | G73: Note 3.2.1.2.a.1
D74: 2. Adjustments | E74: Net amount | F74: Adjustments
D75: (a) Covered Tax accrued as an expense in the profit before taxation in the financial accounts - Article 4.1.2 (a) | E75: =+M294 -> 0 | F75: GIR2401 | G75: GIR2701 | H75: Note 3.2.1.2.a.2.a
D76: (b) GloBE Loss Deferred Tax Asset established under Article 4.5.1 or used – Article 4.1.2 (b) combined with Article 4.5.3 | E76: 0 | G76: GIR2702 | H76: Note 3.2.1.2.a.2.b | I76: Article 4.5 provides an elective rule to effectively carry GloBE losses forward with a deemed deferred tax asset. When elected, Article 4.5 applies in lieu of the Article 4.4 modified deferred tax accounting rules. Accordingly, Article 4.5 is generally expected to be of greatest utility as a simplification in jurisdictions that do not impose a corporate income tax or impose one at a very low rate given that when the election is made, Article 4.4 no longer applies and temporary differences may result in Top-up Tax.
D77: (c) Covered Taxes for uncertain tax position recorded as a reduction to Covered Taxes in prior year – Article 4.1.2 (c) | E77: =+M295 -> 0 | F77: GIR2402 | G77: GIR2703 | H77: Note 3.2.1.2.a.2.c
D78: (d) Qualified Refundable Tax Credit or Marketable Transferable Tax Credits recorded as a reduction to current tax expense – Article 4.1.2 (d) | E78: =+M296 -> 0 | F78: GIR2403 | G78: GIR2704 | H78: Note 3.2.1.2.a.2.d
D79: (e) Qualified Flow-through Tax Benefits of Qualified Ownership Interests – Article 3.2.1 (c) | E79: =+M297 -> 0 | F79: GIR2404 | G79: GIR2705 | H79: Note 3.2.1.2.a.2.e
D80: (f) Current tax expense on income excluded from GloBE Income or Loss – Article 4.1.3 (a) | E80: =+M298 -> 0 | F80: GIR2405 | G80: GIR2706 | H80: Note 3.2.1.2.a.2.f
D81: (g) Non-Qualified Refundable Tax Credit, Non-Marketable Transferable Tax Credit or Other Tax Credits not recorded as a reduction to current tax expense – Article 4.1.3 (b) | E81: =+M299 -> 0 | F81: GIR2406 | G81: GIR2707 | H81: Note 3.2.1.2.a.2.g
D82: (h) Covered Taxes refunded or credited (except for any Qualified Refundable Tax Credit, or Marketable Transferable Tax Credits) not treated as an adjustment to current tax expense – Article 4.1.3 (c) | E82: =+M300 -> 0 | F82: GIR2407 | G82: GIR2708 | H82: Note 3.2.1.2.a.2.h
D83: (i) Current tax expense related to uncertain tax position– Article 4.1.3 (d) | E83: =+M301 -> 0 | F83: GIR2408 | G83: GIR2709 | H83: Note 3.2.1.2.a.2.i
D84: (j) Current tax expense not expected to be paid within three years – Article 4.1.3 (e) | E84: =+M302 -> 0 | F84: GIR2409 | G84: GIR2710 | H84: Note 3.2.1.2.a.2.j
D85: (k) Post-filing adjustments – Article 4.6.1 | E85: =+M303 -> 0 | F85: GIR2410 | G85: GIR2711 | H85: Note 3.2.1.2.a.2.k
D86: (l) Covered Taxes relating to Net Asset Gain or Net Asset Loss – Article 3.2.6 | E86: =+M304 -> 0 | F86: GIR2411 | G86: GIR2712 | H86: Note 3.2.1.2.a.2.l
D87: (m) Reduction of Covered Taxes of the UPE that is a Flow-through Entity – Article 7.1 | E87: =+M305 -> 0 | F87: GIR2412 | G87: GIR2713 | H87: Note 3.2.1.2.a.2.m
D88: (m) Covered Taxes for GloBE Income of the UPE that is reduced under a Deductible Dividend Regime – Article 7.2.2 | E88: =+M306 -> 0 | F88: GIR2413 | G88: GIR2714 | H88: Note 3.2.1.2.a.2.n
... D92: (r) Increase or decrease in Covered Taxes recorded in equity or Other Comprehensive Income relating to amounts included in GloBE Income or Loss that will be subject to tax under local tax rules – Article 4.1.1 (c) | E92: =+M310 -> 0 | F92: GIR2417 | G92: GIR2718 | H92: Note 3.2.1.2.a.2.r
D93: (s) Excess Negative Tax Expense Carry Forward generated – Article 4.1.5 and 5.2.1 | E93: =+E102 -> 0 | F93: GeneratedInRFY | G93: GIR2719 | H93: Note 3.2.1.2.a.2.s
D94: (t) Decrease in Covered Taxes (but not below zero) by the remaining balance of the Excess Negative Tax Expense Carry-forward – Article 4.1.5 and 5.2.1 | E94: =+E101 -> 0 | F94: UtilizedInRFY | G94: GIR2720 | H94: Note 3.2.1.2.a.2.t
D95: 3. Adjusted Covered Taxes | E95: =E73+SUM(E75:E94) -> 234567 | G95: AdjustedCoveredTax
D98: (b) Excess Negative Tax Expense Carry-forward | E98: not applicable | F98: ExcessNegTaxExpense | H98: In a Fiscal Year in which there is no Net GloBE Income for a jurisdiction, if the AdjustedCovered Taxes for a jurisdiction are less than zero and less than the Expected Adjusted CoveredTaxes Amount the Constituent Entities in that jurisdiction shall be treated as having AdditionalCurrent Top-up Tax for the jurisdiction under Article 5.4 arising in the current Fiscal Year equal tothe difference between these amounts. The Expected Adjusted Covered Taxes Amount is equal to the GloBE Income or Loss for a jurisdiction multiplied by the Minimum Rate.
D99: 1. Balance from prior years [A] | E99: 0 | F99: PriorYearBalance | G99: Note 3.2.1.2.b.1
D100: 2. Excess Negative Tax Expense Carry-forward generated in the reporting fiscal year [B] | E100: 0 | F100: GeneratedInRFY | G100: Note 3.2.1.2.b.2
D101: 3. Excess Negative Tax Expense Carry-forward utilized for the reporting fiscal year [C] | E101: 0 | F101: UtilizedInRFY | G101: Note 3.2.1.2.b.3
D102: 4. Excess Negative Tax Expense Carry-forward remaining for subsequent years [D]=[A]+[B]-[C] | E102: =+E99+E100+E101 -> 0 | F102: Remaining | G102: Note 3.2.1.2.b.4
D105: (c) Transitional Blended CFC Regime calculation (if any)
D106: 1. CFC Jurisdictions | E106: 2. Subgroup | F106: 3. Aggregated taxes allocated to that subgroup under a Blended CFC Tax Regime | G106: Note 3.2.1.2.c / Note 3.2.1.2.c.1 / Note 3.2.1.2.c.2 / Note 3.2.1.2.c.3
D107: Please indicate the CFC Jurisdiction if applicable | E107: Please indicate Subgroup if applicable | F107: 0
D108: Please indicate the CFC Jurisdiction if applicable | E108: Please indicate Subgroup if applicable | F108: 0
D109: Total | F109: =+F107+F108 -> 0
D112: 3.2.2 Jurisdictional computations relating to deferred tax accounting | E112: applicable
D113: 3.2.2.1 Deferred Tax adjustments
D114: (a) High-level summary
D115: a. Deferred tax expense in the financial accounts [A] | E115: 1. Deferred tax expense for GloBE purposes before recasting and adjustments | F115: =+M325 -> 3456 | G115: DefTaxAmt | H115: Note 3.2.2.1.a.1.a
D116: b. Deferred tax expense in relation to assets or liabilities for which the GloBE carrying value is different to the accounting carrying value [B] | F116: 0 | G116: DiffCarryValue | H116: Note 3.2.2.1.a.1.b
D117: c. Deferred tax expense based on the GloBE carrying value of assets or liabilities [C] | F117: 0 | G117: GloBEValue | H117: Note 3.2.2.1.a.1.c
D118: d. Deferred tax expense for GloBE purposes before recasting and adjustments [D]=[A]-[B]+[C] | F118: =F115-F116+F117 -> 3456 | G118: BefRecastAdjust | H118: Note 3.2.2.1.a.1.d
D119: 2. Total amount of adjustments [E] | F119: =+E144 -> 0 | G119: TotalAdjust | H119: Note 3.2.2.1.a.2
D120: e. Deferred Tax expense for GloBE purposes before recasting [F]=[D]+[E] | E120: 3. Recasting the deferred tax expense to the Minimum Rate | F120: =+F119+F118 -> 3456 | G120: PreRecast | H120: Note 3.2.2.1.a.3.e
D121: f. Difference between deferred tax expense recorded at a lower tax rate than the Minimum Rate and recast at Minimum Rate [G] | F121: =+M344 -> 0 | G121: Higher | H121: Note 3.2.2.1.a.3.f
D122: g. Difference between the deferred tax expense recorded at a higher tax rate than the Minimum Rate and recast at Minimum Rate [H] | F122: =+M345 -> 0 | G122: Lower | H122: Note 3.2.2.1.a.3.g
D123: 4. Total Deferred Tax Adjustment Amount [I]=[F]+[G]-[H] | F123: =+F120+F121-F122 -> 3456 | G123: DeferTaxAdjustAmt | H123: Note 3.2.2.1.a.4
D126: (b) Breakdown of the adjustments
D127: 1. Adjustments to deferred tax expense | E127: Net amount | F127: AdjustmentItem | G127: Note 3.2.2.1.b
D128: (a) Deferred tax expense related to items excluded from GloBE Income or Loss – Article 4.4.1 (a) | E128: =+M327 -> 0 | F128: GIR2501 | G128: Note 3.2.2.1.b.1.a
D129: (b) Deferred tax expense related to Disallowed Accruals– Article 4.4.1 (b) | E129: =+M328 -> 0 | F129: GIR2502 | G129: Note 3.2.2.1.b.1.b
D130: (c) Deferred tax expense related to Unclaimed Accruals – Article 4.4.1 (b) | E130: =+M329 -> 0 | F130: GIR2503 | G130: Note 3.2.2.1.b.1.c
D131: (d) Valuation adjustment or accounting recognition adjustment related to a deferred tax asset – Article 4.4.1 (c) | E131: =+M330 -> 0 | F131: GIR2504 | G131: Note 3.2.2.1.b.1.d
D132: (e) Deferred tax expense arising from a re-measurement related to changes in the tax rate – Article 4.4.1 (d) | E132: =+M331 -> 0 | F132: GIR2505 | G132: Note 3.2.2.1.b.1.e
D133: (f) Deferred tax expense related to the generation and use of tax credits – Article 4.4.1 (e) | E133: =+M332 -> 0 | F133: GIR2506 | G133: Note 3.2.2.1.b.1.f
D134: (g) Substitute Loss Carry Forward DTA or deemed Substitute Loss Carry Forward DTA – Article 4.4.1 (e) | E134: =+M333 -> 0 | F134: GIR2507 | G134: Note 3.2.2.1.b.1.g
...

Sheet 3 GloBE Computations FI
D2: 3 GloBE Computations
D3: The Filing Constituent Entity shall complete Section 3 on a jurisdictional basis, for each jurisdiction (or subgroup, where relevant) where exceptions to the GloBE computation do not apply
D5: Please make sure that only the yellow marked cells are populated. Don't include or delete any other cell, row or column! | E5: To be populated
D6: References to GloBE Information Return (Pillar Two) XML Schema User Guide for Tax Administrations are in light clue | E6: XML references
D7: Further explanations are in light green | E7: Further explanations
D9: 3.1 Characteristics of the jurisdiction (Information purpose only)
D10: 1. Name of the jurisdiction | E10: Finland
D11: 2. Type of subgroup (if any) - mention "n/a" if no subgroup exists | E11: n/a
D12: 3. Identification of subgroup (if any) for the ETR and Top-up Tax computation - mention "n/a" if no subgroup exists | E12: n/a
D13: 4. Jurisdictions with taxing rights | E13: Finland
D14: 5. ETR | E14: =+E36 -> 0.40442656
D15: 6. Adjusted Covered Taxes | E15: =+E35 -> 234567
D16: 7. Net GloBE Income or Loss | E16: =+E33 -> 579999
D17: 8. Substance-based Income Exclusion | E17: =+E437 -> 341400
D18: 9. Additional Current Top-up Tax | E18: =+E475 -> 0
D19: 10.Top-up Tax amount under domestic legislation | E19: =+E425 -> 0
D20: 11. Elections
D21: 12. Aggregate current tax expense with respect to Covered Taxes after allocations in Article 4.3 | E21: =+E73 -> 234567
D22: 13. Qualified Refundable Tax Credits or Marketable Transferable Tax Credits (tax expense) | E22: =+E78 -> 0
D23: 14. Other tax credits (tax expense) | E23: =+E81 -> 0
D24: 15. Deferred tax expense amount | E24: =+F123 -> 2343
D25: 16. Qualified Refundable Tax Credits or Marketable Transferable Tax Credits (income) | E25: =+E55 -> 0
D26: 17. Excess Negative Tax Expense Carry Forward | E26: =E93 -> 0
D27: 18. Transition Rules
D30: 3.2 ETR computation | E30: applicable
D31: 3.2.1 ETR | E31: applicable | F31: OverallComputation
D32: a. Financial Accounting Net Income or Loss | E32: =+M233 -> 345432 | F32: FANIL | G32: Note 3.2.1.a
D33: b. Net GloBE Income or Loss [A] | E33: =+E68 -> 579999 | F33: NetGlobeIncome | G33: Note 3.2.1.b
D34: c. Income tax expense | E34: =+E42 -> 234567 | F34: IncomeTaxExpense | G34: Note 3.2.1.c
D35: d. Adjusted Covered Taxes [B] | E35: =+M311 -> 234567 | F35: AdjustedCoveredTax | G35: Note 3.2.1.d
D36: e. ETR [C]=[B]/[A] | E36: =+E35/E33 -> 0.40442656 | F36: ETRRate | G36: Note 3.2.1.e
D39: 3.2.1.1 Computation of GloBE Income (Loss) of the Jurisdiction
D40: 1. Aggregate FANIL amount after allocations in Articles 3.4 and 3.5 (All CEs in the jurisdiction) | E40: =+M233 -> 345432 | F40: AdjustedFANIL
D41: 2. Adjustments | E41: Net amount | F41: Adjustments
D42: (a) Net Taxes Expense - Article 3.2.1 (a) | E42: =+M235 -> 234567 | F42: GIR2001 | G42: Note 3.2.1.1.2a
D43: (b) Excluded Dividends – Article 3.2.1 (b) | E43: =+M236 -> 0 | F43: GIR2002 | G43: Note 3.2.1.1.2b
D44: (c) Excluded Equity Gain or Loss – Article 3.2.1 (c) | E44: =+M237 -> 0 | F44: GIR2003 | G44: Note 3.2.1.1.2c
D45: (d) Included Revaluation Method Gain or Loss – Article 3.2.1 (d) | E45: =+M238 -> 0 | F45: GIR2004 | G45: Note 3.2.1.1.2d
D46: (e) Gain or loss from disposition of assets and liabilities excluded under Article 6.3 – Article 3.2.1 (e) | E46: =+M239 -> 0 | F46: GIR2005 | G46: Note 3.2.1.1.2e
D47: (f) Asymmetric Foreign Currency Gains or Losses – Article 3.2.1 (f) | E47: =+M240 -> 0 | F47: GIR2006 | G47: Note 3.2.1.1.2f
D48: (g) Policy Disallowed Expenses – Article 3.2.1 (g) | E48: =+M241 -> 0 | F48: GIR2007 | G48: Note 3.2.1.1.2g
D49: (h) Prior Period Errors – Article 3.2.1 (h) | E49: =+M242 -> 0 | F49: GIR2008 | G49: Note 3.2.1.1.2h
D50: (i) Changes in Accounting Principles – Article 3.2.1(h) | E50: =+M243 -> 0 | F50: GIR2009 | G50: Note 3.2.1.1.2i
D51: (j) Accrued Pension Expense – Article 3.2.1 (i) | E51: =+M244 -> 0 | F51: GIR2010 | G51: Note 3.2.1.1.2j
D52: (k) Debt releases - Article 3.2.1 | E52: =+M245 -> 0 | F52: GIR2011 | G52: Note 3.2.1.1.2k
D53: (l) Stock-based compensation – Article 3.2.2 | E53: =+M246 -> 0 | F53: GIR2012 | G53: Note 3.2.1.1.2l
... D68: 3. Net GloBE Income (Loss) of the Jurisdiction | E68: =+M261 -> 579999 | F68: NetGlobeIncome | G68: Note 3.2.1.1.3
D71: 3.2.1.2 Computation of Adjusted Covered Taxes
D72: (a) Total amount of Adjusted Covered Taxes
D73: 1. Aggregate Current tax expense with respect to Covered Taxes after allocations in Article 4.3 (All CEs in the jurisdiction) | E73: =+M292 -> 234567 | F73: AggregrateCurrentTax | G73: Note 3.2.1.2.a.1
D74: 2. Adjustments | E74: Net amount | F74: Adjustments
D75: (a) Covered Tax accrued as an expense in the profit before taxation in the financial accounts - Article 4.1.2 (a) | E75: =+M294 -> 0 | F75: GIR2401 | G75: GIR2701 | H75: Note 3.2.1.2.a.2.a
D76: (b) GloBE Loss Deferred Tax Asset established under Article 4.5.1 or used – Article 4.1.2 (b) combined with Article 4.5.3 | E76: 0 | G76: GIR2702 | H76: Note 3.2.1.2.a.2.b | I76: Article 4.5 provides an elective rule to effectively carry GloBE losses forward with a deemed deferred tax asset. When elected, Article 4.5 applies in lieu of the Article 4.4 modified deferred tax accounting rules. Accordingly, Article 4.5 is generally expected to be of greatest utility as a simplification in jurisdictions that do not impose a corporate income tax or impose one at a very low rate given that when the election is made, Article 4.4 no longer applies and temporary differences may result in Top-up Tax.
D77: (c) Covered Taxes for uncertain tax position recorded as a reduction to Covered Taxes in prior year – Article 4.1.2 (c) | E77: =+M295 -> 0 | F77: GIR2402 | G77: GIR2703 | H77: Note 3.2.1.2.a.2.c
D78: (d) Qualified Refundable Tax Credit or Marketable Transferable Tax Credits recorded as a reduction to current tax expense – Article 4.1.2 (d) | E78: =+M296 -> 0 | F78: GIR2403 | G78: GIR2704 | H78: Note 3.2.1.2.a.2.d
D79: (e) Qualified Flow-through Tax Benefits of Qualified Ownership Interests – Article 3.2.1 (c) | E79: =+M297 -> 0 | F79: GIR2404 | G79: GIR2705 | H79: Note 3.2.1.2.a.2.e
D80: (f) Current tax expense on income excluded from GloBE Income or Loss – Article 4.1.3 (a) | E80: =+M298 -> 0 | F80: GIR2405 | G80: GIR2706 | H80: Note 3.2.1.2.a.2.f
D81: (g) Non-Qualified Refundable Tax Credit, Non-Marketable Transferable Tax Credit or Other Tax Credits not recorded as a reduction to current tax expense – Article 4.1.3 (b) | E81: =+M299 -> 0 | F81: GIR2406 | G81: GIR2707 | H81: Note 3.2.1.2.a.2.g
D82: (h) Covered Taxes refunded or credited (except for any Qualified Refundable Tax Credit, or Marketable Transferable Tax Credits) not treated as an adjustment to current tax expense – Article 4.1.3 (c) | E82: =+M300 -> 0 | F82: GIR2407 | G82: GIR2708 | H82: Note 3.2.1.2.a.2.h
D83: (i) Current tax expense related to uncertain tax position– Article 4.1.3 (d) | E83: =+M301 -> 0 | F83: GIR2408 | G83: GIR2709 | H83: Note 3.2.1.2.a.2.i
D84: (j) Current tax expense not expected to be paid within three years – Article 4.1.3 (e) | E84: =+M302 -> 0 | F84: GIR2409 | G84: GIR2710 | H84: Note 3.2.1.2.a.2.j
D85: (k) Post-filing adjustments – Article 4.6.1 | E85: =+M303 -> 0 | F85: GIR2410 | G85: GIR2711 | H85: Note 3.2.1.2.a.2.k
D86: (l) Covered Taxes relating to Net Asset Gain or Net Asset Loss – Article 3.2.6 | E86: =+M304 -> 0 | F86: GIR2411 | G86: GIR2712 | H86: Note 3.2.1.2.a.2.l
D87: (m) Reduction of Covered Taxes of the UPE that is a Flow-through Entity – Article 7.1 | E87: =+M305 -> 0 | F87: GIR2412 | G87: GIR2713 | H87: Note 3.2.1.2.a.2.m
D88: (m) Covered Taxes for GloBE Income of the UPE that is reduced under a Deductible Dividend Regime – Article 7.2.2 | E88: =+M306 -> 0 | F88: GIR2413 | G88: GIR2714 | H88: Note 3.2.1.2.a.2.n
... D92: (r) Increase or decrease in Covered Taxes recorded in equity or Other Comprehensive Income relating to amounts included in GloBE Income or Loss that will be subject to tax under local tax rules – Article 4.1.1 (c) | E92: =+M310 -> 0 | F92: GIR2417 | G92: GIR2718 | H92: Note 3.2.1.2.a.2.r
D93: (s) Excess Negative Tax Expense Carry Forward generated – Article 4.1.5 and 5.2.1 | E93: =+E102 -> 0 | F93: GeneratedInRFY | G93: GIR2719 | H93: Note 3.2.1.2.a.2.s
D94: (t) Decrease in Covered Taxes (but not below zero) by the remaining balance of the Excess Negative Tax Expense Carry-forward – Article 4.1.5 and 5.2.1 | E94: =+E101 -> 0 | F94: UtilizedInRFY | G94: GIR2720 | H94: Note 3.2.1.2.a.2.t
D95: 3. Adjusted Covered Taxes | E95: =E73+SUM(E75:E94) -> 234567 | G95: AdjustedCoveredTax
D98: (b) Excess Negative Tax Expense Carry-forward | E98: not applicable | F98: ExcessNegTaxExpense | H98: In a Fiscal Year in which there is no Net GloBE Income for a jurisdiction, if the AdjustedCovered Taxes for a jurisdiction are less than zero and less than the Expected Adjusted CoveredTaxes Amount the Constituent Entities in that jurisdiction shall be treated as having AdditionalCurrent Top-up Tax for the jurisdiction under Article 5.4 arising in the current Fiscal Year equal tothe difference between these amounts. The Expected Adjusted Covered Taxes Amount is equal to the GloBE Income or Loss for a jurisdiction multiplied by the Minimum Rate.
D99: 1. Balance from prior years [A] | E99: 0 | F99: PriorYearBalance | G99: Note 3.2.1.2.b.1
D100: 2. Excess Negative Tax Expense Carry-forward generated in the reporting fiscal year [B] | E100: 0 | F100: GeneratedInRFY | G100: Note 3.2.1.2.b.2
D101: 3. Excess Negative Tax Expense Carry-forward utilized for the reporting fiscal year [C] | E101: 0 | F101: UtilizedInRFY | G101: Note 3.2.1.2.b.3
D102: 4. Excess Negative Tax Expense Carry-forward remaining for subsequent years [D]=[A]+[B]-[C] | E102: =+E99+E100+E101 -> 0 | F102: Remaining | G102: Note 3.2.1.2.b.4
D105: (c) Transitional Blended CFC Regime calculation (if any)
D106: 1. CFC Jurisdictions | E106: 2. Subgroup | F106: 3. Aggregated taxes allocated to that subgroup under a Blended CFC Tax Regime | G106: Note 3.2.1.2.c / Note 3.2.1.2.c.1 / Note 3.2.1.2.c.2 / Note 3.2.1.2.c.3
D107: Please indicate the CFC Jurisdiction if applicable | E107: Please indicate Subgroup if applicable | F107: 0
D108: Please indicate the CFC Jurisdiction if applicable | E108: Please indicate Subgroup if applicable | F108: 0
D109: Total | F109: =+F107+F108 -> 0
D112: 3.2.2 Jurisdictional computations relating to deferred tax accounting | E112: applicable
D113: 3.2.2.1 Deferred Tax adjustments
D114: (a) High-level summary
D115: a. Deferred tax expense in the financial accounts [A] | E115: 1. Deferred tax expense for GloBE purposes before recasting and adjustments | F115: =+M325 -> 2343 | G115: DefTaxAmt | H115: Note 3.2.2.1.a.1.a
D116: b. Deferred tax expense in relation to assets or liabilities for which the GloBE carrying value is different to the accounting carrying value [B] | F116: 0 | G116: DiffCarryValue | H116: Note 3.2.2.1.a.1.b
D117: c. Deferred tax expense based on the GloBE carrying value of assets or liabilities [C] | F117: 0 | G117: GloBEValue | H117: Note 3.2.2.1.a.1.c
D118: d. Deferred tax expense for GloBE purposes before recasting and adjustments [D]=[A]-[B]+[C] | F118: =F115-F116+F117 -> 2343 | G118: BefRecastAdjust | H118: Note 3.2.2.1.a.1.d
D119: 2. Total amount of adjustments [E] | F119: =+E144 -> 0 | G119: TotalAdjust | H119: Note 3.2.2.1.a.2
D120: e. Deferred Tax expense for GloBE purposes before recasting [F]=[D]+[E] | E120: 3. Recasting the deferred tax expense to the Minimum Rate | F120: =+F119+F118 -> 2343 | G120: PreRecast | H120: Note 3.2.2.1.a.3.e
D121: f. Difference between deferred tax expense recorded at a lower tax rate than the Minimum Rate and recast at Minimum Rate [G] | F121: =+M344 -> 0 | G121: Higher | H121: Note 3.2.2.1.a.3.f
D122: g. Difference between the deferred tax expense recorded at a higher tax rate than the Minimum Rate and recast at Minimum Rate [H] | F122: =+M345 -> 0 | G122: Lower | H122: Note 3.2.2.1.a.3.g
D123: 4. Total Deferred Tax Adjustment Amount [I]=[F]+[G]-[H] | F123: =+F120+F121-F122 -> 2343 | G123: DeferTaxAdjustAmt | H123: Note 3.2.2.1.a.4
D126: (b) Breakdown of the adjustments
D127: 1. Adjustments to deferred tax expense | E127: Net amount | F127: AdjustmentItem | G127: Note 3.2.2.1.b
D128: (a) Deferred tax expense related to items excluded from GloBE Income or Loss – Article 4.4.1 (a) | E128: =+M327 -> 0 | F128: GIR2501 | G128: Note 3.2.2.1.b.1.a
D129: (b) Deferred tax expense related to Disallowed Accruals– Article 4.4.1 (b) | E129: =+M328 -> 0 | F129: GIR2502 | G129: Note 3.2.2.1.b.1.b
D130: (c) Deferred tax expense related to Unclaimed Accruals – Article 4.4.1 (b) | E130: =+M329 -> 0 | F130: GIR2503 | G130: Note 3.2.2.1.b.1.c
D131: (d) Valuation adjustment or accounting recognition adjustment related to a deferred tax asset – Article 4.4.1 (c) | E131: =+M330 -> 0 | F131: GIR2504 | G131: Note 3.2.2.1.b.1.d
D132: (e) Deferred tax expense arising from a re-measurement related to changes in the tax rate – Article 4.4.1 (d) | E132: =+M331 -> 0 | F132: GIR2505 | G132: Note 3.2.2.1.b.1.e
D133: (f) Deferred tax expense related to the generation and use of tax credits – Article 4.4.1 (e) | E133: =+M332 -> 0 | F133: GIR2506 | G133: Note 3.2.2.1.b.1.f
D134: (g) Substitute Loss Carry Forward DTA or deemed Substitute Loss Carry Forward DTA – Article 4.4.1 (e) | E134: =+M333 -> 0 | F134: GIR2507 | G134: Note 3.2.2.1.b.1.g
...
